Workbook

Sheet Вводные
A1: ВВОДНЫЕ ДАННЫЕ
A3: Параметр | B3: Значение | C3: Ед. | D3: Комментарий
A4: Название проекта | B4: Жилой проект | D4: Рабочее название
A5: Регион | B5: Якутия | D5: Пользовательский ввод
A6: Класс жилья | B6: Комфорт | D6: Пользовательский ввод
A7: Дата старта проекта | B7: 46054 | C7: дата | D7: Начало модели
A8: Срок строительства | B8: 18 | C8: мес | D8: До ввода
A9: Срок продаж | B9: 16 | C9: мес | D9: Период продаж
A10: GBA | B10: 10795.3 | C10: м2 | D10: Общая площадь здания
A11: GSA | B11: 7860.32 | C11: м2 | D11: Продаваемая площадь
A12: Количество машиномест | B12: 6 | C12: шт | D12: Машиноместа
A13: Цена продажи квартир | B13: 175000 | C13: руб/м2 | D13: Актуализировано по рынку Якутска
A14: Цена машиноместа | B14: 1600000 | C14: руб/шт | D14: Актуализировано по рынку машиномест
A15: Рост цен продаж | B15: 0.08 | C15: % | D15: Годовой рост
A16: Инфляция строительства | B16: 0.076 | C16: % | D16: Годовой рост ставок
A17: Коэффициент региона | B17: 1 | C17: x | D17: Региональная корректировка
A18: Минимальная доля собственных средств | B18: 0.1503 | C18: % | D18: По кредитному договору
... A26: Ставка I(v) >130% | B26: 0.0001 | C26: % | D26: По кредитному договору
A27: Дата окончания отсрочки процентов | B27: =EDATE(B7,B8-1) -> 46569 | C27: дата | D27: Автоматически = месяц ввода (от даты старта и срока строительства)
A28: Дата полного погашения кредита | B28: =EDATE(B7,B8-1) -> 46569 | C28: дата | D28: Автоматически = месяц ввода / закрытия кредита
A29: Целевой DSCR | B29: 1.2 | C29: x | D29: Контрольный ориентир
A31: СТАВКИ ПО ГЛАВЕ 1
A32: 1.1.1 Стоимость покупки права / доли / зданий | C32: руб/м2 GSA | D32: Укрупненно
A33: 1.1.2 Арендные платежи / земельный налог | C33: руб/м2 GSA | D33: Укрупненно
A34: 1.2 Изменение ВРИ | C34: руб/м2 GSA | D34: Укрупненно
A35: 1.3 Прочие затраты на содержание ЗУ | C35: руб/м2 GSA | D35: Укрупненно
A37: СТАВКИ ПО ГЛАВЕ 2
A38: 2.1 Подготовительный период | B38: 1800 | C38: руб/м2 GSA | D38: Откалибровано под Якутию / апрель 2026
A39: 2.2.1 Земляные работы | B39: 1800 | C39: руб/м2 GBA | D39: Укрупненно
A40: 2.2.2 Фундамент / сваи / ограждение котлована | B40: 7650 | C40: руб/м2 GBA | D40: Укрупненно
A41: 2.2.3 Подземная часть | B41: 0 | C41: руб/м2 GBA | D41: Укрупненно
A42: 2.2.4 Надземная часть | B42: 19900 | C42: руб/м2 GBA | D42: Укрупненно
A43: 2.2.5 Ограждающие конструкции / кровля | B43: 9700 | C43: руб/м2 GBA | D43: Укрупненно
A44: 2.2.6 Отделка МОП и техпомещений | B44: 6050 | C44: руб/м2 GBA | D44: Укрупненно
A45: 2.2.7 Отделка реализуемых площадей | B45: 0 | C45: руб/м2 GSA | D45: Если есть чистовая
A46: 2.2.8 Наружная отделка / проемы | B46: 8600 | C46: руб/м2 GBA | D46: Укрупненно
A47: 2.3.1 Вертикальный транспорт | B47: 520 | C47: руб/м2 GBA | D47: Укрупненно
A48: 2.3.2 Сантехнические системы | B48: 4140 | C48: руб/м2 GBA | D48: Укрупненно
A49: 2.3.3 Отопление / ИТП | B49: 2470 | C49: руб/м2 GBA | D49: Укрупненно
... A61: 2.8 Резерв на непредвиденные | B61: 0.05 | C61: % | D61: % от главы 2 до резерва
A63: СТАВКИ ПО ГЛАВЕ 3
A64: 3.1 Коммерческие расходы | B64: 0.03 | C64: % | D64: % от выручки
A66: НОРМЫ ДЛЯ ПОСТАВОК
A67: Бетон на 1 м2 GBA | B67: 0.42 | C67: м3/м2 | D67: Для графика поставок
A68: Арматура на 1 м2 GBA | B68: 0.048 | C68: т/м2 | D68: Для графика поставок

Sheet Структура_затрат
A1: ФИНАНСОВАЯ МОДЕЛЬ / СТРУКТУРА ЗАТРАТ
J2: Разбивка СМР | K2: Материалы | L2: Работы
A3: Глава | B3: Код | C3: Статья | D3: База | E3: Ед. | F3: Ставка | G3: Коэфф. | H3: Сумма | I3: Примечание | J3: Материалы, % | K3: Материалы | L3: Работы
A4: 1 | B4: 1.1.1 | C4: Стоимость покупки права / доли / зданий | D4: =Вводные!$B11 -> 7860.32 | E4: м2 GSA | G4: =Вводные!$B17 -> 1 | H4: =D4*F4*G4 -> 0
A5: 1 | B5: 1.1.2 | C5: Арендные платежи / земельный налог | D5: =Вводные!$B11 -> 7860.32 | E5: м2 GSA | G5: =Вводные!$B17 -> 1 | H5: =D5*F5*G5 -> 0
A6: 1 | B6: 1.2 | C6: Изменение ВРИ | D6: =Вводные!$B11 -> 7860.32 | E6: м2 GSA | G6: =Вводные!$B17 -> 1 | H6: =D6*F6*G6 -> 0
A7: 1 | B7: 1.3 | C7: Прочие затраты на содержание ЗУ | D7: =Вводные!$B11 -> 7860.32 | E7: м2 GSA | G7: =Вводные!$B17 -> 1 | H7: =D7*F7*G7 -> 0
C8: ИТОГО ГЛАВА 1 | H8: =SUM(H4:H7) -> 0
A9: 2 | B9: 2.1 | C9: Подготовительный период | D9: =Вводные!$B11 -> 7860.32 | E9: м2 GSA | F9: =Вводные!$B38 -> 1800 | G9: =Вводные!$B17 -> 1 | H9: =D9*F9*G9 -> 14148576 | J9: 0.35 | K9: =H9*J9 -> 4952001.6 | L9: =H9-K9 -> 9196574.4
A10: 2 | B10: 2.2.1 | C10: Земляные работы | D10: =Вводные!$B10 -> 10795.3 | E10: м2 GBA | F10: =Вводные!$B39 -> 1800 | G10: =Вводные!$B17 -> 1 | H10: =D10*F10*G10 -> 19431540 | J10: 0.3 | K10: =H10*J10 -> 5829462 | L10: =H10-K10 -> 13602078
A11: 2 | B11: 2.2.2 | C11: Фундаментная плита / свайное основание / ограждение котлована | D11: =Вводные!$B10 -> 10795.3 | E11: м2 GBA | F11: =Вводные!$B40 -> 7650 | G11: =Вводные!$B17 -> 1 | H11: =D11*F11*G11 -> 82584045 | J11: 0.6 | K11: =H11*J11 -> 49550427 | L11: =H11-K11 -> 33033618
A12: 2 | B12: 2.2.3 | C12: Устройство несущих конструкций подземной части | D12: =Вводные!$B10 -> 10795.3 | E12: м2 GBA | F12: =Вводные!$B41 -> 0 | G12: =Вводные!$B17 -> 1 | H12: =D12*F12*G12 -> 0 | J12: 0.6 | K12: =H12*J12 -> 0 | L12: =H12-K12 -> 0
A13: 2 | B13: 2.2.4 | C13: Устройство несущих конструкций надземной части | D13: =Вводные!$B10 -> 10795.3 | E13: м2 GBA | F13: =Вводные!$B42 -> 19900 | G13: =Вводные!$B17 -> 1 | H13: =D13*F13*G13 -> 214826470 | J13: 0.65 | K13: =H13*J13 -> 1.3963721e+08 | L13: =H13-K13 -> 75189264
A14: 2 | B14: 2.2.5 | C14: Ограждающие конструкции / внутренние стены / кровля | D14: =Вводные!$B10 -> 10795.3 | E14: м2 GBA | F14: =Вводные!$B43 -> 9700 | G14: =Вводные!$B17 -> 1 | H14: =D14*F14*G14 -> 104714410 | J14: 0.7 | K14: =H14*J14 -> 73300087 | L14: =H14-K14 -> 31414323
A15: 2 | B15: 2.2.6 | C15: Внутренняя отделка МОП и техпомещений | D15: =Вводные!$B10 -> 10795.3 | E15: м2 GBA | F15: =Вводные!$B44 -> 6050 | G15: =Вводные!$B17 -> 1 | H15: =D15*F15*G15 -> 65311565 | J15: 0.6 | K15: =H15*J15 -> 39186939 | L15: =H15-K15 -> 26124626
A16: 2 | B16: 2.2.7 | C16: Отделка реализуемых площадей | D16: =Вводные!$B11 -> 7860.32 | E16: м2 GSA | F16: =Вводные!$B45 -> 0 | G16: =Вводные!$B17 -> 1 | H16: =D16*F16*G16 -> 0 | J16: 0.65 | K16: =H16*J16 -> 0 | L16: =H16-K16 -> 0
A17: 2 | B17: 2.2.8 | C17: Наружная отделка / заполнение проемов | D17: =Вводные!$B10 -> 10795.3 | E17: м2 GBA | F17: =Вводные!$B46 -> 8600 | G17: =Вводные!$B17 -> 1 | H17: =D17*F17*G17 -> 92839580 | J17: 0.75 | K17: =H17*J17 -> 69629685 | L17: =H17-K17 -> 23209895
A18: 2 | B18: 2.3.1 | C18: Вертикальный транспорт | D18: =Вводные!$B10 -> 10795.3 | E18: м2 GBA | F18: =Вводные!$B47 -> 520 | G18: =Вводные!$B17 -> 1 | H18: =D18*F18*G18 -> 5613556 | J18: 0.8 | K18: =H18*J18 -> 4490844.8 | L18: =H18-K18 -> 1122711.2
A19: 2 | B19: 2.3.2 | C19: Сантехнические системы | D19: =Вводные!$B10 -> 10795.3 | E19: м2 GBA | F19: =Вводные!$B48 -> 4140 | G19: =Вводные!$B17 -> 1 | H19: =D19*F19*G19 -> 44692542 | J19: 0.65 | K19: =H19*J19 -> 29050152 | L19: =H19-K19 -> 15642390
A20: 2 | B20: 2.3.3 | C20: Отопление / ИТП / узел учета | D20: =Вводные!$B10 -> 10795.3 | E20: м2 GBA | F20: =Вводные!$B49 -> 2470 | G20: =Вводные!$B17 -> 1 | H20: =D20*F20*G20 -> 26664391 | J20: 0.6 | K20: =H20*J20 -> 15998635 | L20: =H20-K20 -> 10665756
A21: 2 | B21: 2.3.4 | C21: Вентиляция / кондиционирование / дымоудаление | D21: =Вводные!$B10 -> 10795.3 | E21: м2 GBA | F21: =Вводные!$B50 -> 3420 | G21: =Вводные!$B17 -> 1 | H21: =D21*F21*G21 -> 36919926 | J21: 0.7 | K21: =H21*J21 -> 25843948 | L21: =H21-K21 -> 11075978
A22: 2 | B22: 2.3.5 | C22: Электроснабжение / электроосвещение / слаботочка | D22: =Вводные!$B10 -> 10795.3 | E22: м2 GBA | F22: =Вводные!$B51 -> 5330 | G22: =Вводные!$B17 -> 1 | H22: =D22*F22*G22 -> 57538949 | J22: 0.65 | K22: =H22*J22 -> 37400317 | L22: =H22-K22 -> 20138632
A23: 2 | B23: 2.3.6 | C23: Газоснабжение внутреннее | D23: =Вводные!$B10 -> 10795.3 | E23: м2 GBA | F23: =Вводные!$B52 -> 0 | G23: =Вводные!$B17 -> 1 | H23: =D23*F23*G23 -> 0 | J23: 0.7 | K23: =H23*J23 -> 0 | L23: =H23-K23 -> 0
A24: 2 | B24: 2.4.1 | C24: Наружное водоснабжение / ВЗУ / ТП | D24: =Вводные!$B11 -> 7860.32 | E24: м2 GSA | F24: =Вводные!$B53 -> 960 | G24: =Вводные!$B17 -> 1 | H24: =D24*F24*G24 -> 7545907.2 | J24: 0.6 | K24: =H24*J24 -> 4527544.3 | L24: =H24-K24 -> 3018362.9
A25: 2 | B25: 2.4.2 | C25: Наружные электросети / ТП / связь | D25: =Вводные!$B11 -> 7860.32 | E25: м2 GSA | F25: =Вводные!$B54 -> 1270 | G25: =Вводные!$B17 -> 1 | H25: =D25*F25*G25 -> 9982606.4 | J25: 0.7 | K25: =H25*J25 -> 6987824.5 | L25: =H25-K25 -> 2994781.9
A26: 2 | B26: 2.4.3 | C26: Наружное теплоснабжение / ЦТП / котельная | D26: =Вводные!$B11 -> 7860.32 | E26: м2 GSA | F26: =Вводные!$B55 -> 720 | G26: =Вводные!$B17 -> 1 | H26: =D26*F26*G26 -> 5659430.4 | J26: 0.65 | K26: =H26*J26 -> 3678629.8 | L26: =H26-K26 -> 1980800.6
A27: 2 | B27: 2.4.4 | C27: Бытовая и ливневая канализация | D27: =Вводные!$B11 -> 7860.32 | E27: м2 GSA | F27: =Вводные!$B56 -> 640 | G27: =Вводные!$B17 -> 1 | H27: =D27*F27*G27 -> 5030604.8 | J27: 0.6 | K27: =H27*J27 -> 3018362.9 | L27: =H27-K27 -> 2012241.9
A28: 2 | B28: 2.4.5 | C28: Наружное газоснабжение | D28: =Вводные!$B11 -> 7860.32 | E28: м2 GSA | F28: =Вводные!$B57 -> 0 | G28: =Вводные!$B17 -> 1 | H28: =D28*F28*G28 -> 0 | J28: 0.7 | K28: =H28*J28 -> 0 | L28: =H28-K28 -> 0
A29: 2 | B29: 2.5 | C29: Благоустройство и озеленение | D29: =Вводные!$B10 -> 10795.3 | E29: м2 GBA | F29: =Вводные!$B58 -> 2870 | G29: =Вводные!$B17 -> 1 | H29: =D29*F29*G29 -> 30982511 | J29: 0.5 | K29: =H29*J29 -> 15491255 | L29: =H29-K29 -> 15491255
A30: 2 | B30: 2.6 | C30: Служба заказчика-застройщика / охрана | D30: =SUM(H9:H29) -> 8.2448661e+08 | E30: руб | F30: =Вводные!$B59 -> 0.025 | G30: =1 -> 1 | H30: =D30*F30 -> 20612165
A31: 2 | B31: 2.7 | C31: Проектные и изыскательские работы / экспертиза / авторский надзор | D31: =SUM(H9:H30) -> 8.4509878e+08 | E31: руб | F31: 0.012 | G31: =1 -> 1 | H31: =D31*F31 -> 10141185
A32: 2 | B32: 2.8 | C32: Резерв на непредвиденные расходы | D32: =SUM(H9:H31) -> 8.5523996e+08 | E32: руб | F32: =Вводные!$B61 -> 0.05 | G32: =1 -> 1 | H32: =D32*F32 -> 42761998
A33: 2 | B33: 2.9 | C33: Резерв на инфляционное удорожание | D33: =SUM(H9:H32) -> 8.9800196e+08 | E33: руб | F33: =Вводные!$B16*(Вводные!$B8/12) -> 0.114 | G33: =1 -> 1 | H33: =D33*F33 -> 1.0237222e+08
C34: ИТОГО ГЛАВА 2 | H34: =SUM(H9:H33) -> 1.0003742e+09
A35: 3 | B35: 3.1 | C35: Коммерческие расходы | D35: =Продажи!N41 -> 1.4741871e+09 | E35: руб | F35: =Вводные!$B64 -> 0.03 | G35: =1 -> 1 | H35: =D35*F35 -> 44225613
C36: ИТОГО ГЛАВА 3 | H36: =H35 -> 44225613
C37: ИТОГО СТОИМОСТЬ ПРОЕКТА | H37: =H8+H34+H36 -> 1.0445998e+09
C39: ИТОГО СМР (2.1–2.5) | H39: =SUM(H9:H29) -> 8.2448661e+08 | K39: =SUM(K9:K29) -> 5.2857332e+08 | L39: =SUM(L9:L29) -> 2.9591329e+08
C40: ИТОГО материалы СМР | K40: =SUM(K9:K29) -> 5.2857332e+08
C41: ИТОГО работы СМР | L41: =SUM(L9:L29) -> 2.9591329e+08

Sheet ГПР
A1: ГРАФИК ПРОИЗВОДСТВА РАБОТ
A2: Сроки этапов привязаны к Вводные!B8 (Срок строительства)
A3: Этап | B3: Начало, мес | C3: Длительность, мес | D3: Окончание, мес | E3: Стоимость | F3: 1 | G3: 2 | H3: 3 | I3: 4 | J3: 5 | K3: 6 | L3: 7 | M3: 8 | N3: 9 | O3: 10 | P3: 11 | Q3: 12 | R3: 13 | S3: 14 | T3: 15 | U3: 16 | V3: 17 | W3: 18 | X3: 19 | Y3: 20 | Z3: 21 | AA3: 22 | AB3: 23 | AC3: 24 | AD3: 25 | AE3: 26 | AF3: 27 | AG3: 28 | AH3: 29 | AI3: 30 | AJ3: 31 | AK3: 32 | AL3: 33 | AM3: 34 | AN3: 35 | AO3: 36
A4: Подготовительный период | B4: =1 -> 1 | C4: =MAX(1,ROUNDUP(Вводные!$B$8*0.1,0)) -> 2 | D4: =B4+C4-1 -> 2 | E4: =Структура_затрат!H9 -> 14148576 | F4: =IF(AND(F$3>=$B4,F$3<=$D4),$E4/$C4,0) -> 7074288 | G4: =IF(AND(G$3>=$B4,G$3<=$D4),$E4/$C4,0) -> 7074288 | H4: =IF(AND(H$3>=$B4,H$3<=$D4),$E4/$C4,0) -> 0 | I4: =IF(AND(I$3>=$B4,I$3<=$D4),$E4/$C4,0) -> 0 | J4: =IF(AND(J$3>=$B4,J$3<=$D4),$E4/$C4,0) -> 0 | K4: =IF(AND(K$3>=$B4,K$3<=$D4),$E4/$C4,0) -> 0 | L4: =IF(AND(L$3>=$B4,L$3<=$D4),$E4/$C4,0) -> 0 | M4: =IF(AND(M$3>=$B4,M$3<=$D4),$E4/$C4,0) -> 0 | ... AO4: =IF(AND(AO$3>=$B4,AO$3<=$D4),$E4/$C4,0) -> 0
A5: Земляные работы | B5: =MAX(1,ROUNDUP(Вводные!$B$8*0.08,0)) -> 2 | C5: =MAX(1,ROUNDUP(Вводные!$B$8*0.1,0)) -> 2 | D5: =B5+C5-1 -> 3 | E5: =Структура_затрат!H10 -> 19431540 | F5: =IF(AND(F$3>=$B5,F$3<=$D5),$E5/$C5,0) -> 0 | G5: =IF(AND(G$3>=$B5,G$3<=$D5),$E5/$C5,0) -> 9715770 | H5: =IF(AND(H$3>=$B5,H$3<=$D5),$E5/$C5,0) -> 9715770 | I5: =IF(AND(I$3>=$B5,I$3<=$D5),$E5/$C5,0) -> 0 | J5: =IF(AND(J$3>=$B5,J$3<=$D5),$E5/$C5,0) -> 0 | K5: =IF(AND(K$3>=$B5,K$3<=$D5),$E5/$C5,0) -> 0 | L5: =IF(AND(L$3>=$B5,L$3<=$D5),$E5/$C5,0) -> 0 | M5: =IF(AND(M$3>=$B5,M$3<=$D5),$E5/$C5,0) -> 0 | ... AO5: =IF(AND(AO$3>=$B5,AO$3<=$D5),$E5/$C5,0) -> 0
A6: Фундамент / сваи / котлован | B6: =MAX(1,ROUNDUP(Вводные!$B$8*0.12,0)) -> 3 | C6: =MAX(1,ROUNDUP(Вводные!$B$8*0.15,0)) -> 3 | D6: =B6+C6-1 -> 5 | E6: =Структура_затрат!H11 -> 82584045 | F6: =IF(AND(F$3>=$B6,F$3<=$D6),$E6/$C6,0) -> 0 | G6: =IF(AND(G$3>=$B6,G$3<=$D6),$E6/$C6,0) -> 0 | H6: =IF(AND(H$3>=$B6,H$3<=$D6),$E6/$C6,0) -> 27528015 | I6: =IF(AND(I$3>=$B6,I$3<=$D6),$E6/$C6,0) -> 27528015 | J6: =IF(AND(J$3>=$B6,J$3<=$D6),$E6/$C6,0) -> 27528015 | K6: =IF(AND(K$3>=$B6,K$3<=$D6),$E6/$C6,0) -> 0 | L6: =IF(AND(L$3>=$B6,L$3<=$D6),$E6/$C6,0) -> 0 | M6: =IF(AND(M$3>=$B6,M$3<=$D6),$E6/$C6,0) -> 0 | ... AO6: =IF(AND(AO$3>=$B6,AO$3<=$D6),$E6/$C6,0) -> 0
A7: Подземная часть | B7: =MAX(1,ROUNDUP(Вводные!$B$8*0.18,0)) -> 4 | C7: =MAX(1,ROUNDUP(Вводные!$B$8*0.15,0)) -> 3 | D7: =B7+C7-1 -> 6 | E7: =Структура_затрат!H12 -> 0 | F7: =IF(AND(F$3>=$B7,F$3<=$D7),$E7/$C7,0) -> 0 | G7: =IF(AND(G$3>=$B7,G$3<=$D7),$E7/$C7,0) -> 0 | H7: =IF(AND(H$3>=$B7,H$3<=$D7),$E7/$C7,0) -> 0 | I7: =IF(AND(I$3>=$B7,I$3<=$D7),$E7/$C7,0) -> 0 | J7: =IF(AND(J$3>=$B7,J$3<=$D7),$E7/$C7,0) -> 0 | K7: =IF(AND(K$3>=$B7,K$3<=$D7),$E7/$C7,0) -> 0 | L7: =IF(AND(L$3>=$B7,L$3<=$D7),$E7/$C7,0) -> 0 | M7: =IF(AND(M$3>=$B7,M$3<=$D7),$E7/$C7,0) -> 0 | ... AO7: =IF(AND(AO$3>=$B7,AO$3<=$D7),$E7/$C7,0) -> 0
A8: Надземная часть | B8: =MAX(1,ROUNDUP(Вводные!$B$8*0.25,0)) -> 5 | C8: =MAX(1,ROUNDUP(Вводные!$B$8*0.45,0)) -> 9 | D8: =B8+C8-1 -> 13 | E8: =Структура_затрат!H13 -> 214826470 | F8: =IF(AND(F$3>=$B8,F$3<=$D8),$E8/$C8,0) -> 0 | G8: =IF(AND(G$3>=$B8,G$3<=$D8),$E8/$C8,0) -> 0 | H8: =IF(AND(H$3>=$B8,H$3<=$D8),$E8/$C8,0) -> 0 | I8: =IF(AND(I$3>=$B8,I$3<=$D8),$E8/$C8,0) -> 0 | J8: =IF(AND(J$3>=$B8,J$3<=$D8),$E8/$C8,0) -> 23869608 | K8: =IF(AND(K$3>=$B8,K$3<=$D8),$E8/$C8,0) -> 23869608 | L8: =IF(AND(L$3>=$B8,L$3<=$D8),$E8/$C8,0) -> 23869608 | M8: =IF(AND(M$3>=$B8,M$3<=$D8),$E8/$C8,0) -> 23869608 | ... AO8: =IF(AND(AO$3>=$B8,AO$3<=$D8),$E8/$C8,0) -> 0
A9: Фасады / кровля / проемы | B9: =MAX(1,ROUNDUP(Вводные!$B$8*0.45,0)) -> 9 | C9: =MAX(1,ROUNDUP(Вводные!$B$8*0.33,0)) -> 6 | D9: =B9+C9-1 -> 14 | E9: =Структура_затрат!H14+Структура_затрат!H17 -> 197553990 | F9: =IF(AND(F$3>=$B9,F$3<=$D9),$E9/$C9,0) -> 0 | G9: =IF(AND(G$3>=$B9,G$3<=$D9),$E9/$C9,0) -> 0 | H9: =IF(AND(H$3>=$B9,H$3<=$D9),$E9/$C9,0) -> 0 | I9: =IF(AND(I$3>=$B9,I$3<=$D9),$E9/$C9,0) -> 0 | J9: =IF(AND(J$3>=$B9,J$3<=$D9),$E9/$C9,0) -> 0 | K9: =IF(AND(K$3>=$B9,K$3<=$D9),$E9/$C9,0) -> 0 | L9: =IF(AND(L$3>=$B9,L$3<=$D9),$E9/$C9,0) -> 0 | M9: =IF(AND(M$3>=$B9,M$3<=$D9),$E9/$C9,0) -> 0 | ... AO9: =IF(AND(AO$3>=$B9,AO$3<=$D9),$E9/$C9,0) -> 0
A10: Инженерные системы | B10: =MAX(1,ROUNDUP(Вводные!$B$8*0.48,0)) -> 9 | C10: =MAX(1,ROUNDUP(Вводные!$B$8*0.37,0)) -> 7 | D10: =B10+C10-1 -> 15 | E10: =SUM(Структура_затрат!H18:H22) -> 171429364 | F10: =IF(AND(F$3>=$B10,F$3<=$D10),$E10/$C10,0) -> 0 | G10: =IF(AND(G$3>=$B10,G$3<=$D10),$E10/$C10,0) -> 0 | H10: =IF(AND(H$3>=$B10,H$3<=$D10),$E10/$C10,0) -> 0 | I10: =IF(AND(I$3>=$B10,I$3<=$D10),$E10/$C10,0) -> 0 | J10: =IF(AND(J$3>=$B10,J$3<=$D10),$E10/$C10,0) -> 0 | K10: =IF(AND(K$3>=$B10,K$3<=$D10),$E10/$C10,0) -> 0 | L10: =IF(AND(L$3>=$B10,L$3<=$D10),$E10/$C10,0) -> 0 | M10: =IF(AND(M$3>=$B10,M$3<=$D10),$E10/$C10,0) -> 0 | ... AO10: =IF(AND(AO$3>=$B10,AO$3<=$D10),$E10/$C10,0) -> 0
A11: Отделка МОП / техпомещений / реализуемых площадей | B11: =MAX(1,ROUNDUP(Вводные!$B$8*0.56,0)) -> 11 | C11: =MAX(1,ROUNDUP(Вводные!$B$8*0.33,0)) -> 6 | D11: =B11+C11-1 -> 16 | E11: =Структура_затрат!H15+Структура_затрат!H16 -> 65311565 | F11: =IF(AND(F$3>=$B11,F$3<=$D11),$E11/$C11,0) -> 0 | G11: =IF(AND(G$3>=$B11,G$3<=$D11),$E11/$C11,0) -> 0 | H11: =IF(AND(H$3>=$B11,H$3<=$D11),$E11/$C11,0) -> 0 | I11: =IF(AND(I$3>=$B11,I$3<=$D11),$E11/$C11,0) -> 0 | J11: =IF(AND(J$3>=$B11,J$3<=$D11),$E11/$C11,0) -> 0 | K11: =IF(AND(K$3>=$B11,K$3<=$D11),$E11/$C11,0) -> 0 | L11: =IF(AND(L$3>=$B11,L$3<=$D11),$E11/$C11,0) -> 0 | M11: =IF(AND(M$3>=$B11,M$3<=$D11),$E11/$C11,0) -> 0 | ... AO11: =IF(AND(AO$3>=$B11,AO$3<=$D11),$E11/$C11,0) -> 0
A12: Наружные сети | B12: =MAX(1,ROUNDUP(Вводные!$B$8*0.52,0)) -> 10 | C12: =MAX(1,ROUNDUP(Вводные!$B$8*0.3,0)) -> 6 | D12: =B12+C12-1 -> 15 | E12: =SUM(Структура_затрат!H24:H28) -> 28218549 | F12: =IF(AND(F$3>=$B12,F$3<=$D12),$E12/$C12,0) -> 0 | G12: =IF(AND(G$3>=$B12,G$3<=$D12),$E12/$C12,0) -> 0 | H12: =IF(AND(H$3>=$B12,H$3<=$D12),$E12/$C12,0) -> 0 | I12: =IF(AND(I$3>=$B12,I$3<=$D12),$E12/$C12,0) -> 0 | J12: =IF(AND(J$3>=$B12,J$3<=$D12),$E12/$C12,0) -> 0 | K12: =IF(AND(K$3>=$B12,K$3<=$D12),$E12/$C12,0) -> 0 | L12: =IF(AND(L$3>=$B12,L$3<=$D12),$E12/$C12,0) -> 0 | M12: =IF(AND(M$3>=$B12,M$3<=$D12),$E12/$C12,0) -> 0 | ... AO12: =IF(AND(AO$3>=$B12,AO$3<=$D12),$E12/$C12,0) -> 0
A13: Благоустройство и озеленение | B13: =MAX(1,ROUNDUP(Вводные!$B$8*0.82,0)) -> 15 | C13: =MAX(1,ROUNDUP(Вводные!$B$8*0.15,0)) -> 3 | D13: =B13+C13-1 -> 17 | E13: =Структура_затрат!H29 -> 30982511 | F13: =IF(AND(F$3>=$B13,F$3<=$D13),$E13/$C13,0) -> 0 | G13: =IF(AND(G$3>=$B13,G$3<=$D13),$E13/$C13,0) -> 0 | H13: =IF(AND(H$3>=$B13,H$3<=$D13),$E13/$C13,0) -> 0 | I13: =IF(AND(I$3>=$B13,I$3<=$D13),$E13/$C13,0) -> 0 | J13: =IF(AND(J$3>=$B13,J$3<=$D13),$E13/$C13,0) -> 0 | K13: =IF(AND(K$3>=$B13,K$3<=$D13),$E13/$C13,0) -> 0 | L13: =IF(AND(L$3>=$B13,L$3<=$D13),$E13/$C13,0) -> 0 | M13: =IF(AND(M$3>=$B13,M$3<=$D13),$E13/$C13,0) -> 0 | ... AO13: =IF(AND(AO$3>=$B13,AO$3<=$D13),$E13/$C13,0) -> 0
A14: Заказчик / проектирование / резервы | B14: =1 -> 1 | C14: =MAX(1,Вводные!$B$8) -> 18 | D14: =B14+C14-1 -> 18 | E14: =SUM(Структура_затрат!H30:H33) -> 1.7588757e+08 | F14: =SUM(F4:F13) -> 7074288 | G14: =SUM(G4:G13) -> 16790058 | H14: =SUM(H4:H13) -> 37243785 | I14: =SUM(I4:I13) -> 27528015 | J14: =SUM(J4:J13) -> 51397623 | K14: =SUM(K4:K13) -> 23869608 | L14: =SUM(L4:L13) -> 23869608 | M14: =SUM(M4:M13) -> 23869608 | ... AO14: =SUM(AO4:AO13) -> 0
A16: ИТОГО CAPEX В МЕСЯЦ | F16: =SUM(F4:F14) -> 14148576 | G16: =SUM(G4:G14) -> 33580116 | H16: =SUM(H4:H14) -> 74487570 | I16: =SUM(I4:I14) -> 55056030 | J16: =SUM(J4:J14) -> 1.0279525e+08 | K16: =SUM(K4:K14) -> 47739216 | L16: =SUM(L4:L14) -> 47739216 | M16: =SUM(M4:M14) -> 47739216 | ... AO16: =SUM(AO4:AO14) -> 0

Sheet Продажи
A1: ПРОДАЖИ И ВЫРУЧКА
A3: Месяц | B3: Дата | C3: Вес продаж | D3: Доля | E3: Продано, м2 | F3: Цена, руб/м2 | G3: Выручка квартир | H3: Продано м/мест | I3: Выручка м/мест | J3: Итого выручка | K3: Накопленная выручка | L3: Эскроу накопленно | M3: Раскрытие эскроу | N3: Итого выручка проекта | O3: Средняя цена | P3: Доступно на обслуживание долга
A4: 1 | B4: 46054 | C4: 1 | D4: =IF($A4<=Вводные!$B9,C4/SUMPRODUCT(($A$4:$A$39<=Вводные!$B9)*$C$4:$C$39),0) -> 0.019230769 | E4: =IF($A4<=Вводные!$B9,Вводные!$B11*D4,0) -> 151.16 | F4: =Вводные!$B13*(1+Вводные!$B15)^((A4-1)/12) -> 175000 | G4: =E4*F4 -> 26453000 | H4: =IF(AND($A4>=MAX(1,Вводные!$B9-MIN(6,Вводные!$B9)+1),$A4<=Вводные!$B9),Вводные!$B12/MIN(6,Вводные!$B9),0) -> 0 | I4: =H4*Вводные!$B14 -> 0 | J4: =G4+I4 -> 26453000 | K4: =SUM($J$4:J4) -> 26453000 | L4: =K4 -> 26453000 | M4: =IF(AND(YEAR(B4)=YEAR(Вводные!$B$28),MONTH(B4)=MONTH(Вводные!$B$28)),L4,0) -> 0 | N4: =J4 -> 26453000 | O4: =IF(E4=0,0,G4/E4) -> 175000 | P4: =IF(B4<Вводные!$B$28,0,IF(AND(YEAR(B4)=YEAR(Вводные!$B$28),MONTH(B4)=MONTH(Вводные!$B$28)),M4,J4)) -> 0
A5: 2 | B5: 46082 | C5: 1 | D5: =IF($A5<=Вводные!$B9,C5/SUMPRODUCT(($A$4:$A$39<=Вводные!$B9)*$C$4:$C$39),0) -> 0.019230769 | E5: =IF($A5<=Вводные!$B9,Вводные!$B11*D5,0) -> 151.16 | F5: =Вводные!$B13*(1+Вводные!$B15)^((A5-1)/12) -> 176125.96 | G5: =E5*F5 -> 26623199 | H5: =IF(AND($A5>=MAX(1,Вводные!$B9-MIN(6,Вводные!$B9)+1),$A5<=Вводные!$B9),Вводные!$B12/MIN(6,Вводные!$B9),0) -> 0 | I5: =H5*Вводные!$B14 -> 0 | J5: =G5+I5 -> 26623199 | K5: =SUM($J$4:J5) -> 53076199 | L5: =K5 -> 53076199 | M5: =IF(AND(YEAR(B5)=YEAR(Вводные!$B$28),MONTH(B5)=MONTH(Вводные!$B$28)),L5,0) -> 0 | N5: =J5 -> 26623199 | O5: =IF(E5=0,0,G5/E5) -> 176125.96 | P5: =IF(B5<Вводные!$B$28,0,IF(AND(YEAR(B5)=YEAR(Вводные!$B$28),MONTH(B5)=MONTH(Вводные!$B$28)),M5,J5)) -> 0
A6: 3 | B6: 46113 | C6: 1 | D6: =IF($A6<=Вводные!$B9,C6/SUMPRODUCT(($A$4:$A$39<=Вводные!$B9)*$C$4:$C$39),0) -> 0.019230769 | E6: =IF($A6<=Вводные!$B9,Вводные!$B11*D6,0) -> 151.16 | F6: =Вводные!$B13*(1+Вводные!$B15)^((A6-1)/12) -> 177259.15 | G6: =E6*F6 -> 26794494 | H6: =IF(AND($A6>=MAX(1,Вводные!$B9-MIN(6,Вводные!$B9)+1),$A6<=Вводные!$B9),Вводные!$B12/MIN(6,Вводные!$B9),0) -> 0 | I6: =H6*Вводные!$B14 -> 0 | J6: =G6+I6 -> 26794494 | K6: =SUM($J$4:J6) -> 79870693 | L6: =K6 -> 79870693 | M6: =IF(AND(YEAR(B6)=YEAR(Вводные!$B$28),MONTH(B6)=MONTH(Вводные!$B$28)),L6,0) -> 0 | N6: =J6 -> 26794494 | O6: =IF(E6=0,0,G6/E6) -> 177259.15 | P6: =IF(B6<Вводные!$B$28,0,IF(AND(YEAR(B6)=YEAR(Вводные!$B$28),MONTH(B6)=MONTH(Вводные!$B$28)),M6,J6)) -> 0
A7: 4 | B7: 46143 | C7: 1 | D7: =IF($A7<=Вводные!$B9,C7/SUMPRODUCT(($A$4:$A$39<=Вводные!$B9)*$C$4:$C$39),0) -> 0.019230769 | E7: =IF($A7<=Вводные!$B9,Вводные!$B11*D7,0) -> 151.16 | F7: =Вводные!$B13*(1+Вводные!$B15)^((A7-1)/12) -> 178399.65 | G7: =E7*F7 -> 26966890 | H7: =IF(AND($A7>=MAX(1,Вводные!$B9-MIN(6,Вводные!$B9)+1),$A7<=Вводные!$B9),Вводные!$B12/MIN(6,Вводные!$B9),0) -> 0 | I7: =H7*Вводные!$B14 -> 0 | J7: =G7+I7 -> 26966890 | K7: =SUM($J$4:J7) -> 1.0683758e+08 | L7: =K7 -> 1.0683758e+08 | M7: =IF(AND(YEAR(B7)=YEAR(Вводные!$B$28),MONTH(B7)=MONTH(Вводные!$B$28)),L7,0) -> 0 | N7: =J7 -> 26966890 | O7: =IF(E7=0,0,G7/E7) -> 178399.65 | P7: =IF(B7<Вводные!$B$28,0,IF(AND(YEAR(B7)=YEAR(Вводные!$B$28),MONTH(B7)=MONTH(Вводные!$B$28)),M7,J7)) -> 0
A8: 5 | B8: 46174 | C8: 2 | D8: =IF($A8<=Вводные!$B9,C8/SUMPRODUCT(($A$4:$A$39<=Вводные!$B9)*$C$4:$C$39),0) -> 0.038461538 | E8: =IF($A8<=Вводные!$B9,Вводные!$B11*D8,0) -> 302.32 | F8: =Вводные!$B13*(1+Вводные!$B15)^((A8-1)/12) -> 179547.47 | G8: =E8*F8 -> 54280792 | H8: =IF(AND($A8>=MAX(1,Вводные!$B9-MIN(6,Вводные!$B9)+1),$A8<=Вводные!$B9),Вводные!$B12/MIN(6,Вводные!$B9),0) -> 0 | I8: =H8*Вводные!$B14 -> 0 | J8: =G8+I8 -> 54280792 | K8: =SUM($J$4:J8) -> 1.6111838e+08 | L8: =K8 -> 1.6111838e+08 | M8: =IF(AND(YEAR(B8)=YEAR(Вводные!$B$28),MONTH(B8)=MONTH(Вводные!$B$28)),L8,0) -> 0 | N8: =J8 -> 54280792 | O8: =IF(E8=0,0,G8/E8) -> 179547.47 | P8: =IF(B8<Вводные!$B$28,0,IF(AND(YEAR(B8)=YEAR(Вводные!$B$28),MONTH(B8)=MONTH(Вводные!$B$28)),M8,J8)) -> 0
A9: 6 | B9: 46204 | C9: 2 | D9: =IF($A9<=Вводные!$B9,C9/SUMPRODUCT(($A$4:$A$39<=Вводные!$B9)*$C$4:$C$39),0) -> 0.038461538 | E9: =IF($A9<=Вводные!$B9,Вводные!$B11*D9,0) -> 302.32 | F9: =Вводные!$B13*(1+Вводные!$B15)^((A9-1)/12) -> 180702.69 | G9: =E9*F9 -> 54630037 | H9: =IF(AND($A9>=MAX(1,Вводные!$B9-MIN(6,Вводные!$B9)+1),$A9<=Вводные!$B9),Вводные!$B12/MIN(6,Вводные!$B9),0) -> 0 | I9: =H9*Вводные!$B14 -> 0 | J9: =G9+I9 -> 54630037 | K9: =SUM($J$4:J9) -> 2.1574841e+08 | L9: =K9 -> 2.1574841e+08 | M9: =IF(AND(YEAR(B9)=YEAR(Вводные!$B$28),MONTH(B9)=MONTH(Вводные!$B$28)),L9,0) -> 0 | N9: =J9 -> 54630037 | O9: =IF(E9=0,0,G9/E9) -> 180702.69 | P9: =IF(B9<Вводные!$B$28,0,IF(AND(YEAR(B9)=YEAR(Вводные!$B$28),MONTH(B9)=MONTH(Вводные!$B$28)),M9,J9)) -> 0
A10: 7 | B10: 46235 | C10: 3 | D10: =IF($A10<=Вводные!$B9,C10/SUMPRODUCT(($A$4:$A$39<=Вводные!$B9)*$C$4:$C$39),0) -> 0.057692308 | E10: =IF($A10<=Вводные!$B9,Вводные!$B11*D10,0) -> 453.48 | F10: =Вводные!$B13*(1+Вводные!$B15)^((A10-1)/12) -> 181865.33 | G10: =E10*F10 -> 82472292 | H10: =IF(AND($A10>=MAX(1,Вводные!$B9-MIN(6,Вводные!$B9)+1),$A10<=Вводные!$B9),Вводные!$B12/MIN(6,Вводные!$B9),0) -> 0 | I10: =H10*Вводные!$B14 -> 0 | J10: =G10+I10 -> 82472292 | K10: =SUM($J$4:J10) -> 2.982207e+08 | L10: =K10 -> 2.982207e+08 | M10: =IF(AND(YEAR(B10)=YEAR(Вводные!$B$28),MONTH(B10)=MONTH(Вводные!$B$28)),L10,0) -> 0 | N10: =J10 -> 82472292 | O10: =IF(E10=0,0,G10/E10) -> 181865.33 | P10: =IF(B10<Вводные!$B$28,0,IF(AND(YEAR(B10)=YEAR(Вводные!$B$28),MONTH(B10)=MONTH(Вводные!$B$28)),M10,J10)) -> 0
A11: 8 | B11: 46266 | C11: 3 | D11: =IF($A11<=Вводные!$B9,C11/SUMPRODUCT(($A$4:$A$39<=Вводные!$B9)*$C$4:$C$39),0) -> 0.057692308 | E11: =IF($A11<=Вводные!$B9,Вводные!$B11*D11,0) -> 453.48 | F11: =Вводные!$B13*(1+Вводные!$B15)^((A11-1)/12) -> 183035.46 | G11: =E11*F11 -> 83002921 | H11: =IF(AND($A11>=MAX(1,Вводные!$B9-MIN(6,Вводные!$B9)+1),$A11<=Вводные!$B9),Вводные!$B12/MIN(6,Вводные!$B9),0) -> 0 | I11: =H11*Вводные!$B14 -> 0 | J11: =G11+I11 -> 83002921 | K11: =SUM($J$4:J11) -> 3.8122363e+08 | L11: =K11 -> 3.8122363e+08 | M11: =IF(AND(YEAR(B11)=YEAR(Вводные!$B$28),MONTH(B11)=MONTH(Вводные!$B$28)),L11,0) -> 0 | N11: =J11 -> 83002921 | O11: =IF(E11=0,0,G11/E11) -> 183035.46 | P11: =IF(B11<Вводные!$B$28,0,IF(AND(YEAR(B11)=YEAR(Вводные!$B$28),MONTH(B11)=MONTH(Вводные!$B$28)),M11,J11)) -> 0
A12: 9 | B12: 46296 | C12: 4 | D12: =IF($A12<=Вводные!$B9,C12/SUMPRODUCT(($A$4:$A$39<=Вводные!$B9)*$C$4:$C$39),0) -> 0.076923077 | E12: =IF($A12<=Вводные!$B9,Вводные!$B11*D12,0) -> 604.64 | F12: =Вводные!$B13*(1+Вводные!$B15)^((A12-1)/12) -> 184213.12 | G12: =E12*F12 -> 1.1138262e+08 | H12: =IF(AND($A12>=MAX(1,Вводные!$B9-MIN(6,Вводные!$B9)+1),$A12<=Вводные!$B9),Вводные!$B12/MIN(6,Вводные!$B9),0) -> 0 | I12: =H12*Вводные!$B14 -> 0 | J12: =G12+I12 -> 1.1138262e+08 | K12: =SUM($J$4:J12) -> 4.9260625e+08 | L12: =K12 -> 4.9260625e+08 | M12: =IF(AND(YEAR(B12)=YEAR(Вводные!$B$28),MONTH(B12)=MONTH(Вводные!$B$28)),L12,0) -> 0 | N12: =J12 -> 1.1138262e+08 | O12: =IF(E12=0,0,G12/E12) -> 184213.12 | P12: =IF(B12<Вводные!$B$28,0,IF(AND(YEAR(B12)=YEAR(Вводные!$B$28),MONTH(B12)=MONTH(Вводные!$B$28)),M12,J12)) -> 0
A13: 10 | B13: 46327 | C13: 4 | D13: =IF($A13<=Вводные!$B9,C13/SUMPRODUCT(($A$4:$A$39<=Вводные!$B9)*$C$4:$C$39),0) -> 0.076923077 | E13: =IF($A13<=Вводные!$B9,Вводные!$B11*D13,0) -> 604.64 | F13: =Вводные!$B13*(1+Вводные!$B15)^((A13-1)/12) -> 185398.35 | G13: =E13*F13 -> 1.1209926e+08 | H13: =IF(AND($A13>=MAX(1,Вводные!$B9-MIN(6,Вводные!$B9)+1),$A13<=Вводные!$B9),Вводные!$B12/MIN(6,Вводные!$B9),0) -> 0 | I13: =H13*Вводные!$B14 -> 0 | J13: =G13+I13 -> 1.1209926e+08 | K13: =SUM($J$4:J13) -> 6.047055e+08 | L13: =K13 -> 6.047055e+08 | M13: =IF(AND(YEAR(B13)=YEAR(Вводные!$B$28),MONTH(B13)=MONTH(Вводные!$B$28)),L13,0) -> 0 | N13: =J13 -> 1.1209926e+08 | O13: =IF(E13=0,0,G13/E13) -> 185398.35 | P13: =IF(B13<Вводные!$B$28,0,IF(AND(YEAR(B13)=YEAR(Вводные!$B$28),MONTH(B13)=MONTH(Вводные!$B$28)),M13,J13)) -> 0
A14: 11 | B14: 46357 | C14: 5 | D14: =IF($A14<=Вводные!$B9,C14/SUMPRODUCT(($A$4:$A$39<=Вводные!$B9)*$C$4:$C$39),0) -> 0.096153846 | E14: =IF($A14<=Вводные!$B9,Вводные!$B11*D14,0) -> 755.8 | F14: =Вводные!$B13*(1+Вводные!$B15)^((A14-1)/12) -> 186591.21 | G14: =E14*F14 -> 1.4102564e+08 | H14: =IF(AND($A14>=MAX(1,Вводные!$B9-MIN(6,Вводные!$B9)+1),$A14<=Вводные!$B9),Вводные!$B12/MIN(6,Вводные!$B9),0) -> 1 | I14: =H14*Вводные!$B14 -> 1600000 | J14: =G14+I14 -> 1.4262564e+08 | K14: =SUM($J$4:J14) -> 7.4733114e+08 | L14: =K14 -> 7.4733114e+08 | M14: =IF(AND(YEAR(B14)=YEAR(Вводные!$B$28),MONTH(B14)=MONTH(Вводные!$B$28)),L14,0) -> 0 | N14: =J14 -> 1.4262564e+08 | O14: =IF(E14=0,0,G14/E14) -> 186591.21 | P14: =IF(B14<Вводные!$B$28,0,IF(AND(YEAR(B14)=YEAR(Вводные!$B$28),MONTH(B14)=MONTH(Вводные!$B$28)),M14,J14)) -> 0
A15: 12 | B15: 46388 | C15: 5 | D15: =IF($A15<=Вводные!$B9,C15/SUMPRODUCT(($A$4:$A$39<=Вводные!$B9)*$C$4:$C$39),0) -> 0.096153846 | E15: =IF($A15<=Вводные!$B9,Вводные!$B11*D15,0) -> 755.8 | F15: =Вводные!$B13*(1+Вводные!$B15)^((A15-1)/12) -> 187791.74 | G15: =E15*F15 -> 1.41933e+08 | H15: =IF(AND($A15>=MAX(1,Вводные!$B9-MIN(6,Вводные!$B9)+1),$A15<=Вводные!$B9),Вводные!$B12/MIN(6,Вводные!$B9),0) -> 1 | I15: =H15*Вводные!$B14 -> 1600000 | J15: =G15+I15 -> 1.43533e+08 | K15: =SUM($J$4:J15) -> 8.9086414e+08 | L15: =K15 -> 8.9086414e+08 | M15: =IF(AND(YEAR(B15)=YEAR(Вводные!$B$28),MONTH(B15)=MONTH(Вводные!$B$28)),L15,0) -> 0 | N15: =J15 -> 1.43533e+08 | O15: =IF(E15=0,0,G15/E15) -> 187791.74 | P15: =IF(B15<Вводные!$B$28,0,IF(AND(YEAR(B15)=YEAR(Вводные!$B$28),MONTH(B15)=MONTH(Вводные!$B$28)),M15,J15)) -> 0
A16: 13 | B16: 46419 | C16: 5 | D16: =IF($A16<=Вводные!$B9,C16/SUMPRODUCT(($A$4:$A$39<=Вводные!$B9)*$C$4:$C$39),0) -> 0.096153846 | E16: =IF($A16<=Вводные!$B9,Вводные!$B11*D16,0) -> 755.8 | F16: =Вводные!$B13*(1+Вводные!$B15)^((A16-1)/12) -> 189000 | G16: =E16*F16 -> 142846200 | H16: =IF(AND($A16>=MAX(1,Вводные!$B9-MIN(6,Вводные!$B9)+1),$A16<=Вводные!$B9),Вводные!$B12/MIN(6,Вводные!$B9),0) -> 1 | I16: =H16*Вводные!$B14 -> 1600000 | J16: =G16+I16 -> 144446200 | K16: =SUM($J$4:J16) -> 1.0353103e+09 | L16: =K16 -> 1.0353103e+09 | M16: =IF(AND(YEAR(B16)=YEAR(Вводные!$B$28),MONTH(B16)=MONTH(Вводные!$B$28)),L16,0) -> 0 | N16: =J16 -> 144446200 | O16: =IF(E16=0,0,G16/E16) -> 189000 | P16: =IF(B16<Вводные!$B$28,0,IF(AND(YEAR(B16)=YEAR(Вводные!$B$28),MONTH(B16)=MONTH(Вводные!$B$28)),M16,J16)) -> 0
A17: 14 | B17: 46447 | C17: 5 | D17: =IF($A17<=Вводные!$B9,C17/SUMPRODUCT(($A$4:$A$39<=Вводные!$B9)*$C$4:$C$39),0) -> 0.096153846 | E17: =IF($A17<=Вводные!$B9,Вводные!$B11*D17,0) -> 755.8 | F17: =Вводные!$B13*(1+Вводные!$B15)^((A17-1)/12) -> 190216.03 | G17: =E17*F17 -> 1.4376528e+08 | H17: =IF(AND($A17>=MAX(1,Вводные!$B9-MIN(6,Вводные!$B9)+1),$A17<=Вводные!$B9),Вводные!$B12/MIN(6,Вводные!$B9),0) -> 1 | I17: =H17*Вводные!$B14 -> 1600000 | J17: =G17+I17 -> 1.4536528e+08 | K17: =SUM($J$4:J17) -> 1.1806756e+09 | L17: =K17 -> 1.1806756e+09 | M17: =IF(AND(YEAR(B17)=YEAR(Вводные!$B$28),MONTH(B17)=MONTH(Вводные!$B$28)),L17,0) -> 0 | N17: =J17 -> 1.4536528e+08 | O17: =IF(E17=0,0,G17/E17) -> 190216.03 | P17: =IF(B17<Вводные!$B$28,0,IF(AND(YEAR(B17)=YEAR(Вводные!$B$28),MONTH(B17)=MONTH(Вводные!$B$28)),M17,J17)) -> 0
A18: 15 | B18: 46478 | C18: 5 | D18: =IF($A18<=Вводные!$B9,C18/SUMPRODUCT(($A$4:$A$39<=Вводные!$B9)*$C$4:$C$39),0) -> 0.096153846 | E18: =IF($A18<=Вводные!$B9,Вводные!$B11*D18,0) -> 755.8 | F18: =Вводные!$B13*(1+Вводные!$B15)^((A18-1)/12) -> 191439.89 | G18: =E18*F18 -> 1.4469027e+08 | H18: =IF(AND($A18>=MAX(1,Вводные!$B9-MIN(6,Вводные!$B9)+1),$A18<=Вводные!$B9),Вводные!$B12/MIN(6,Вводные!$B9),0) -> 1 | I18: =H18*Вводные!$B14 -> 1600000 | J18: =G18+I18 -> 1.4629027e+08 | K18: =SUM($J$4:J18) -> 1.3269659e+09 | L18: =K18 -> 1.3269659e+09 | M18: =IF(AND(YEAR(B18)=YEAR(Вводные!$B$28),MONTH(B18)=MONTH(Вводные!$B$28)),L18,0) -> 0 | N18: =J18 -> 1.4629027e+08 | O18: =IF(E18=0,0,G18/E18) -> 191439.89 | P18: =IF(B18<Вводные!$B$28,0,IF(AND(YEAR(B18)=YEAR(Вводные!$B$28),MONTH(B18)=MONTH(Вводные!$B$28)),M18,J18)) -> 0
A19: 16 | B19: 46508 | C19: 5 | D19: =IF($A19<=Вводные!$B9,C19/SUMPRODUCT(($A$4:$A$39<=Вводные!$B9)*$C$4:$C$39),0) -> 0.096153846 | E19: =IF($A19<=Вводные!$B9,Вводные!$B11*D19,0) -> 755.8 | F19: =Вводные!$B13*(1+Вводные!$B15)^((A19-1)/12) -> 192671.62 | G19: =E19*F19 -> 1.4562121e+08 | H19: =IF(AND($A19>=MAX(1,Вводные!$B9-MIN(6,Вводные!$B9)+1),$A19<=Вводные!$B9),Вводные!$B12/MIN(6,Вводные!$B9),0) -> 1 | I19: =H19*Вводные!$B14 -> 1600000 | J19: =G19+I19 -> 1.4722121e+08 | K19: =SUM($J$4:J19) -> 1.4741871e+09 | L19: =K19 -> 1.4741871e+09 | M19: =IF(AND(YEAR(B19)=YEAR(Вводные!$B$28),MONTH(B19)=MONTH(Вводные!$B$28)),L19,0) -> 0 | N19: =J19 -> 1.4722121e+08 | O19: =IF(E19=0,0,G19/E19) -> 192671.62 | P19: =IF(B19<Вводные!$B$28,0,IF(AND(YEAR(B19)=YEAR(Вводные!$B$28),MONTH(B19)=MONTH(Вводные!$B$28)),M19,J19)) -> 0
A20: 17 | B20: 46539 | C20: 4 | D20: =IF($A20<=Вводные!$B9,C20/SUMPRODUCT(($A$4:$A$39<=Вводные!$B9)*$C$4:$C$39),0) -> 0 | E20: =IF($A20<=Вводные!$B9,Вводные!$B11*D20,0) -> 0 | F20: =Вводные!$B13*(1+Вводные!$B15)^((A20-1)/12) -> 193911.27 | G20: =E20*F20 -> 0 | H20: =IF(AND($A20>=MAX(1,Вводные!$B9-MIN(6,Вводные!$B9)+1),$A20<=Вводные!$B9),Вводные!$B12/MIN(6,Вводные!$B9),0) -> 0 | I20: =H20*Вводные!$B14 -> 0 | J20: =G20+I20 -> 0 | K20: =SUM($J$4:J20) -> 1.4741871e+09 | L20: =K20 -> 1.4741871e+09 | M20: =IF(AND(YEAR(B20)=YEAR(Вводные!$B$28),MONTH(B20)=MONTH(Вводные!$B$28)),L20,0) -> 0 | N20: =J20 -> 0 | O20: =IF(E20=0,0,G20/E20) -> 0 | P20: =IF(B20<Вводные!$B$28,0,IF(AND(YEAR(B20)=YEAR(Вводные!$B$28),MONTH(B20)=MONTH(Вводные!$B$28)),M20,J20)) -> 0
A21: 18 | B21: 46569 | C21: 4 | D21: =IF($A21<=Вводные!$B9,C21/SUMPRODUCT(($A$4:$A$39<=Вводные!$B9)*$C$4:$C$39),0) -> 0 | E21: =IF($A21<=Вводные!$B9,Вводные!$B11*D21,0) -> 0 | F21: =Вводные!$B13*(1+Вводные!$B15)^((A21-1)/12) -> 195158.9 | G21: =E21*F21 -> 0 | H21: =IF(AND($A21>=MAX(1,Вводные!$B9-MIN(6,Вводные!$B9)+1),$A21<=Вводные!$B9),Вводные!$B12/MIN(6,Вводные!$B9),0) -> 0 | I21: =H21*Вводные!$B14 -> 0 | J21: =G21+I21 -> 0 | K21: =SUM($J$4:J21) -> 1.4741871e+09 | L21: =K21 -> 1.4741871e+09 | M21: =IF(AND(YEAR(B21)=YEAR(Вводные!$B$28),MONTH(B21)=MONTH(Вводные!$B$28)),L21,0) -> 1.4741871e+09 | N21: =J21 -> 0 | O21: =IF(E21=0,0,G21/E21) -> 0 | P21: =IF(B21<Вводные!$B$28,0,IF(AND(YEAR(B21)=YEAR(Вводные!$B$28),MONTH(B21)=MONTH(Вводные!$B$28)),M21,J21)) -> 1.4741871e+09
A22: 19 | B22: 46600 | C22: 4 | D22: =IF($A22<=Вводные!$B9,C22/SUMPRODUCT(($A$4:$A$39<=Вводные!$B9)*$C$4:$C$39),0) -> 0 | E22: =IF($A22<=Вводные!$B9,Вводные!$B11*D22,0) -> 0 | F22: =Вводные!$B13*(1+Вводные!$B15)^((A22-1)/12) -> 196414.56 | G22: =E22*F22 -> 0 | H22: =IF(AND($A22>=MAX(1,Вводные!$B9-MIN(6,Вводные!$B9)+1),$A22<=Вводные!$B9),Вводные!$B12/MIN(6,Вводные!$B9),0) -> 0 | I22: =H22*Вводные!$B14 -> 0 | J22: =G22+I22 -> 0 | K22: =SUM($J$4:J22) -> 1.4741871e+09 | L22: =K22 -> 1.4741871e+09 | M22: =IF(AND(YEAR(B22)=YEAR(Вводные!$B$28),MONTH(B22)=MONTH(Вводные!$B$28)),L22,0) -> 0 | N22: =J22 -> 0 | O22: =IF(E22=0,0,G22/E22) -> 0 | P22: =IF(B22<Вводные!$B$28,0,IF(AND(YEAR(B22)=YEAR(Вводные!$B$28),MONTH(B22)=MONTH(Вводные!$B$28)),M22,J22)) -> 0
A23: 20 | B23: 46631 | C23: 4 | D23: =IF($A23<=Вводные!$B9,C23/SUMPRODUCT(($A$4:$A$39<=Вводные!$B9)*$C$4:$C$39),0) -> 0 | E23: =IF($A23<=Вводные!$B9,Вводные!$B11*D23,0) -> 0 | F23: =Вводные!$B13*(1+Вводные!$B15)^((A23-1)/12) -> 197678.3 | G23: =E23*F23 -> 0 | H23: =IF(AND($A23>=MAX(1,Вводные!$B9-MIN(6,Вводные!$B9)+1),$A23<=Вводные!$B9),Вводные!$B12/MIN(6,Вводные!$B9),0) -> 0 | I23: =H23*Вводные!$B14 -> 0 | J23: =G23+I23 -> 0 | K23: =SUM($J$4:J23) -> 1.4741871e+09 | L23: =K23 -> 1.4741871e+09 | M23: =IF(AND(YEAR(B23)=YEAR(Вводные!$B$28),MONTH(B23)=MONTH(Вводные!$B$28)),L23,0) -> 0 | N23: =J23 -> 0 | O23: =IF(E23=0,0,G23/E23) -> 0 | P23: =IF(B23<Вводные!$B$28,0,IF(AND(YEAR(B23)=YEAR(Вводные!$B$28),MONTH(B23)=MONTH(Вводные!$B$28)),M23,J23)) -> 0
A24: 21 | B24: 46661 | C24: 3 | D24: =IF($A24<=Вводные!$B9,C24/SUMPRODUCT(($A$4:$A$39<=Вводные!$B9)*$C$4:$C$39),0) -> 0 | E24: =IF($A24<=Вводные!$B9,Вводные!$B11*D24,0) -> 0 | F24: =Вводные!$B13*(1+Вводные!$B15)^((A24-1)/12) -> 198950.17 | G24: =E24*F24 -> 0 | H24: =IF(AND($A24>=MAX(1,Вводные!$B9-MIN(6,Вводные!$B9)+1),$A24<=Вводные!$B9),Вводные!$B12/MIN(6,Вводные!$B9),0) -> 0 | I24: =H24*Вводные!$B14 -> 0 | J24: =G24+I24 -> 0 | K24: =SUM($J$4:J24) -> 1.4741871e+09 | L24: =K24 -> 1.4741871e+09 | M24: =IF(AND(YEAR(B24)=YEAR(Вводные!$B$28),MONTH(B24)=MONTH(Вводные!$B$28)),L24,0) -> 0 | N24: =J24 -> 0 | O24: =IF(E24=0,0,G24/E24) -> 0 | P24: =IF(B24<Вводные!$B$28,0,IF(AND(YEAR(B24)=YEAR(Вводные!$B$28),MONTH(B24)=MONTH(Вводные!$B$28)),M24,J24)) -> 0
A25: 22 | B25: 46692 | C25: 3 | D25: =IF($A25<=Вводные!$B9,C25/SUMPRODUCT(($A$4:$A$39<=Вводные!$B9)*$C$4:$C$39),0) -> 0 | E25: =IF($A25<=Вводные!$B9,Вводные!$B11*D25,0) -> 0 | F25: =Вводные!$B13*(1+Вводные!$B15)^((A25-1)/12) -> 200230.22 | G25: =E25*F25 -> 0 | H25: =IF(AND($A25>=MAX(1,Вводные!$B9-MIN(6,Вводные!$B9)+1),$A25<=Вводные!$B9),Вводные!$B12/MIN(6,Вводные!$B9),0) -> 0 | I25: =H25*Вводные!$B14 -> 0 | J25: =G25+I25 -> 0 | K25: =SUM($J$4:J25) -> 1.4741871e+09 | L25: =K25 -> 1.4741871e+09 | M25: =IF(AND(YEAR(B25)=YEAR(Вводные!$B$28),MONTH(B25)=MONTH(Вводные!$B$28)),L25,0) -> 0 | N25: =J25 -> 0 | O25: =IF(E25=0,0,G25/E25) -> 0 | P25: =IF(B25<Вводные!$B$28,0,IF(AND(YEAR(B25)=YEAR(Вводные!$B$28),MONTH(B25)=MONTH(Вводные!$B$28)),M25,J25)) -> 0
A26: 23 | B26: 46722 | C26: 3 | D26: =IF($A26<=Вводные!$B9,C26/SUMPRODUCT(($A$4:$A$39<=Вводные!$B9)*$C$4:$C$39),0) -> 0 | E26: =IF($A26<=Вводные!$B9,Вводные!$B11*D26,0) -> 0 | F26: =Вводные!$B13*(1+Вводные!$B15)^((A26-1)/12) -> 201518.51 | G26: =E26*F26 -> 0 | H26: =IF(AND($A26>=MAX(1,Вводные!$B9-MIN(6,Вводные!$B9)+1),$A26<=Вводные!$B9),Вводные!$B12/MIN(6,Вводные!$B9),0) -> 0 | I26: =H26*Вводные!$B14 -> 0 | J26: =G26+I26 -> 0 | K26: =SUM($J$4:J26) -> 1.4741871e+09 | L26: =K26 -> 1.4741871e+09 | M26: =IF(AND(YEAR(B26)=YEAR(Вводные!$B$28),MONTH(B26)=MONTH(Вводные!$B$28)),L26,0) -> 0 | N26: =J26 -> 0 | O26: =IF(E26=0,0,G26/E26) -> 0 | P26: =IF(B26<Вводные!$B$28,0,IF(AND(YEAR(B26)=YEAR(Вводные!$B$28),MONTH(B26)=MONTH(Вводные!$B$28)),M26,J26)) -> 0
A27: 24 | B27: 46753 | C27: 2 | D27: =IF($A27<=Вводные!$B9,C27/SUMPRODUCT(($A$4:$A$39<=Вводные!$B9)*$C$4:$C$39),0) -> 0 | E27: =IF($A27<=Вводные!$B9,Вводные!$B11*D27,0) -> 0 | F27: =Вводные!$B13*(1+Вводные!$B15)^((A27-1)/12) -> 202815.08 | G27: =E27*F27 -> 0 | H27: =IF(AND($A27>=MAX(1,Вводные!$B9-MIN(6,Вводные!$B9)+1),$A27<=Вводные!$B9),Вводные!$B12/MIN(6,Вводные!$B9),0) -> 0 | I27: =H27*Вводные!$B14 -> 0 | J27: =G27+I27 -> 0 | K27: =SUM($J$4:J27) -> 1.4741871e+09 | L27: =K27 -> 1.4741871e+09 | M27: =IF(AND(YEAR(B27)=YEAR(Вводные!$B$28),MONTH(B27)=MONTH(Вводные!$B$28)),L27,0) -> 0 | N27: =J27 -> 0 | O27: =IF(E27=0,0,G27/E27) -> 0 | P27: =IF(B27<Вводные!$B$28,0,IF(AND(YEAR(B27)=YEAR(Вводные!$B$28),MONTH(B27)=MONTH(Вводные!$B$28)),M27,J27)) -> 0
A28: 25 | B28: 46784 | C28: 2 | D28: =IF($A28<=Вводные!$B9,C28/SUMPRODUCT(($A$4:$A$39<=Вводные!$B9)*$C$4:$C$39),0) -> 0 | E28: =IF($A28<=Вводные!$B9,Вводные!$B11*D28,0) -> 0 | F28: =Вводные!$B13*(1+Вводные!$B15)^((A28-1)/12) -> 204120 | G28: =E28*F28 -> 0 | H28: =IF(AND($A28>=MAX(1,Вводные!$B9-MIN(6,Вводные!$B9)+1),$A28<=Вводные!$B9),Вводные!$B12/MIN(6,Вводные!$B9),0) -> 0 | I28: =H28*Вводные!$B14 -> 0 | J28: =G28+I28 -> 0 | K28: =SUM($J$4:J28) -> 1.4741871e+09 | L28: =K28 -> 1.4741871e+09 | M28: =IF(AND(YEAR(B28)=YEAR(Вводные!$B$28),MONTH(B28)=MONTH(Вводные!$B$28)),L28,0) -> 0 | N28: =J28 -> 0 | O28: =IF(E28=0,0,G28/E28) -> 0 | P28: =IF(B28<Вводные!$B$28,0,IF(AND(YEAR(B28)=YEAR(Вводные!$B$28),MONTH(B28)=MONTH(Вводные!$B$28)),M28,J28)) -> 0
A29: 26 | B29: 46813 | C29: 2 | D29: =IF($A29<=Вводные!$B9,C29/SUMPRODUCT(($A$4:$A$39<=Вводные!$B9)*$C$4:$C$39),0) -> 0 | E29: =IF($A29<=Вводные!$B9,Вводные!$B11*D29,0) -> 0 | F29: =Вводные!$B13*(1+Вводные!$B15)^((A29-1)/12) -> 205433.31 | G29: =E29*F29 -> 0 | H29: =IF(AND($A29>=MAX(1,Вводные!$B9-MIN(6,Вводные!$B9)+1),$A29<=Вводные!$B9),Вводные!$B12/MIN(6,Вводные!$B9),0) -> 0 | I29: =H29*Вводные!$B14 -> 0 | J29: =G29+I29 -> 0 | K29: =SUM($J$4:J29) -> 1.4741871e+09 | L29: =K29 -> 1.4741871e+09 | M29: =IF(AND(YEAR(B29)=YEAR(Вводные!$B$28),MONTH(B29)=MONTH(Вводные!$B$28)),L29,0) -> 0 | N29: =J29 -> 0 | O29: =IF(E29=0,0,G29/E29) -> 0 | P29: =IF(B29<Вводные!$B$28,0,IF(AND(YEAR(B29)=YEAR(Вводные!$B$28),MONTH(B29)=MONTH(Вводные!$B$28)),M29,J29)) -> 0
A30: 27 | B30: 46844 | C30: 1 | D30: =IF($A30<=Вводные!$B9,C30/SUMPRODUCT(($A$4:$A$39<=Вводные!$B9)*$C$4:$C$39),0) -> 0 | E30: =IF($A30<=Вводные!$B9,Вводные!$B11*D30,0) -> 0 | F30: =Вводные!$B13*(1+Вводные!$B15)^((A30-1)/12) -> 206755.08 | G30: =E30*F30 -> 0 | H30: =IF(AND($A30>=MAX(1,Вводные!$B9-MIN(6,Вводные!$B9)+1),$A30<=Вводные!$B9),Вводные!$B12/MIN(6,Вводные!$B9),0) -> 0 | I30: =H30*Вводные!$B14 -> 0 | J30: =G30+I30 -> 0 | K30: =SUM($J$4:J30) -> 1.4741871e+09 | L30: =K30 -> 1.4741871e+09 | M30: =IF(AND(YEAR(B30)=YEAR(Вводные!$B$28),MONTH(B30)=MONTH(Вводные!$B$28)),L30,0) -> 0 | N30: =J30 -> 0 | O30: =IF(E30=0,0,G30/E30) -> 0 | P30: =IF(B30<Вводные!$B$28,0,IF(AND(YEAR(B30)=YEAR(Вводные!$B$28),MONTH(B30)=MONTH(Вводные!$B$28)),M30,J30)) -> 0
A31: 28 | B31: 46874 | C31: 1 | D31: =IF($A31<=Вводные!$B9,C31/SUMPRODUCT(($A$4:$A$39<=Вводные!$B9)*$C$4:$C$39),0) -> 0 | E31: =IF($A31<=Вводные!$B9,Вводные!$B11*D31,0) -> 0 | F31: =Вводные!$B13*(1+Вводные!$B15)^((A31-1)/12) -> 208085.35 | G31: =E31*F31 -> 0 | H31: =IF(AND($A31>=MAX(1,Вводные!$B9-MIN(6,Вводные!$B9)+1),$A31<=Вводные!$B9),Вводные!$B12/MIN(6,Вводные!$B9),0) -> 0 | I31: =H31*Вводные!$B14 -> 0 | J31: =G31+I31 -> 0 | K31: =SUM($J$4:J31) -> 1.4741871e+09 | L31: =K31 -> 1.4741871e+09 | M31: =IF(AND(YEAR(B31)=YEAR(Вводные!$B$28),MONTH(B31)=MONTH(Вводные!$B$28)),L31,0) -> 0 | N31: =J31 -> 0 | O31: =IF(E31=0,0,G31/E31) -> 0 | P31: =IF(B31<Вводные!$B$28,0,IF(AND(YEAR(B31)=YEAR(Вводные!$B$28),MONTH(B31)=MONTH(Вводные!$B$28)),M31,J31)) -> 0
A32: 29 | B32: 46905 | C32: 1 | D32: =IF($A32<=Вводные!$B9,C32/SUMPRODUCT(($A$4:$A$39<=Вводные!$B9)*$C$4:$C$39),0) -> 0 | E32: =IF($A32<=Вводные!$B9,Вводные!$B11*D32,0) -> 0 | F32: =Вводные!$B13*(1+Вводные!$B15)^((A32-1)/12) -> 209424.17 | G32: =E32*F32 -> 0 | H32: =IF(AND($A32>=MAX(1,Вводные!$B9-MIN(6,Вводные!$B9)+1),$A32<=Вводные!$B9),Вводные!$B12/MIN(6,Вводные!$B9),0) -> 0 | I32: =H32*Вводные!$B14 -> 0 | J32: =G32+I32 -> 0 | K32: =SUM($J$4:J32) -> 1.4741871e+09 | L32: =K32 -> 1.4741871e+09 | M32: =IF(AND(YEAR(B32)=YEAR(Вводные!$B$28),MONTH(B32)=MONTH(Вводные!$B$28)),L32,0) -> 0 | N32: =J32 -> 0 | O32: =IF(E32=0,0,G32/E32) -> 0 | P32: =IF(B32<Вводные!$B$28,0,IF(AND(YEAR(B32)=YEAR(Вводные!$B$28),MONTH(B32)=MONTH(Вводные!$B$28)),M32,J32)) -> 0
A33: 30 | B33: 46935 | C33: 1 | D33: =IF($A33<=Вводные!$B9,C33/SUMPRODUCT(($A$4:$A$39<=Вводные!$B9)*$C$4:$C$39),0) -> 0 | E33: =IF($A33<=Вводные!$B9,Вводные!$B11*D33,0) -> 0 | F33: =Вводные!$B13*(1+Вводные!$B15)^((A33-1)/12) -> 210771.62 | G33: =E33*F33 -> 0 | H33: =IF(AND($A33>=MAX(1,Вводные!$B9-MIN(6,Вводные!$B9)+1),$A33<=Вводные!$B9),Вводные!$B12/MIN(6,Вводные!$B9),0) -> 0 | I33: =H33*Вводные!$B14 -> 0 | J33: =G33+I33 -> 0 | K33: =SUM($J$4:J33) -> 1.4741871e+09 | L33: =K33 -> 1.4741871e+09 | M33: =IF(AND(YEAR(B33)=YEAR(Вводные!$B$28),MONTH(B33)=MONTH(Вводные!$B$28)),L33,0) -> 0 | N33: =J33 -> 0 | O33: =IF(E33=0,0,G33/E33) -> 0 | P33: =IF(B33<Вводные!$B$28,0,IF(AND(YEAR(B33)=YEAR(Вводные!$B$28),MONTH(B33)=MONTH(Вводные!$B$28)),M33,J33)) -> 0
A34: 31 | B34: 46966 | C34: 0 | D34: =IF($A34<=Вводные!$B9,C34/SUMPRODUCT(($A$4:$A$39<=Вводные!$B9)*$C$4:$C$39),0) -> 0 | E34: =IF($A34<=Вводные!$B9,Вводные!$B11*D34,0) -> 0 | F34: =Вводные!$B13*(1+Вводные!$B15)^((A34-1)/12) -> 212127.73 | G34: =E34*F34 -> 0 | H34: =IF(AND($A34>=MAX(1,Вводные!$B9-MIN(6,Вводные!$B9)+1),$A34<=Вводные!$B9),Вводные!$B12/MIN(6,Вводные!$B9),0) -> 0 | I34: =H34*Вводные!$B14 -> 0 | J34: =G34+I34 -> 0 | K34: =SUM($J$4:J34) -> 1.4741871e+09 | L34: =K34 -> 1.4741871e+09 | M34: =IF(AND(YEAR(B34)=YEAR(Вводные!$B$28),MONTH(B34)=MONTH(Вводные!$B$28)),L34,0) -> 0 | N34: =J34 -> 0 | O34: =IF(E34=0,0,G34/E34) -> 0 | P34: =IF(B34<Вводные!$B$28,0,IF(AND(YEAR(B34)=YEAR(Вводные!$B$28),MONTH(B34)=MONTH(Вводные!$B$28)),M34,J34)) -> 0
A35: 32 | B35: 46997 | C35: 0 | D35: =IF($A35<=Вводные!$B9,C35/SUMPRODUCT(($A$4:$A$39<=Вводные!$B9)*$C$4:$C$39),0) -> 0 | E35: =IF($A35<=Вводные!$B9,Вводные!$B11*D35,0) -> 0 | F35: =Вводные!$B13*(1+Вводные!$B15)^((A35-1)/12) -> 213492.56 | G35: =E35*F35 -> 0 | H35: =IF(AND($A35>=MAX(1,Вводные!$B9-MIN(6,Вводные!$B9)+1),$A35<=Вводные!$B9),Вводные!$B12/MIN(6,Вводные!$B9),0) -> 0 | I35: =H35*Вводные!$B14 -> 0 | J35: =G35+I35 -> 0 | K35: =SUM($J$4:J35) -> 1.4741871e+09 | L35: =K35 -> 1.4741871e+09 | M35: =IF(AND(YEAR(B35)=YEAR(Вводные!$B$28),MONTH(B35)=MONTH(Вводные!$B$28)),L35,0) -> 0 | N35: =J35 -> 0 | O35: =IF(E35=0,0,G35/E35) -> 0 | P35: =IF(B35<Вводные!$B$28,0,IF(AND(YEAR(B35)=YEAR(Вводные!$B$28),MONTH(B35)=MONTH(Вводные!$B$28)),M35,J35)) -> 0
A36: 33 | B36: 47027 | C36: 0 | D36: =IF($A36<=Вводные!$B9,C36/SUMPRODUCT(($A$4:$A$39<=Вводные!$B9)*$C$4:$C$39),0) -> 0 | E36: =IF($A36<=Вводные!$B9,Вводные!$B11*D36,0) -> 0 | F36: =Вводные!$B13*(1+Вводные!$B15)^((A36-1)/12) -> 214866.18 | G36: =E36*F36 -> 0 | H36: =IF(AND($A36>=MAX(1,Вводные!$B9-MIN(6,Вводные!$B9)+1),$A36<=Вводные!$B9),Вводные!$B12/MIN(6,Вводные!$B9),0) -> 0 | I36: =H36*Вводные!$B14 -> 0 | J36: =G36+I36 -> 0 | K36: =SUM($J$4:J36) -> 1.4741871e+09 | L36: =K36 -> 1.4741871e+09 | M36: =IF(AND(YEAR(B36)=YEAR(Вводные!$B$28),MONTH(B36)=MONTH(Вводные!$B$28)),L36,0) -> 0 | N36: =J36 -> 0 | O36: =IF(E36=0,0,G36/E36) -> 0 | P36: =IF(B36<Вводные!$B$28,0,IF(AND(YEAR(B36)=YEAR(Вводные!$B$28),MONTH(B36)=MONTH(Вводные!$B$28)),M36,J36)) -> 0
A37: 34 | B37: 47058 | C37: 0 | D37: =IF($A37<=Вводные!$B9,C37/SUMPRODUCT(($A$4:$A$39<=Вводные!$B9)*$C$4:$C$39),0) -> 0 | E37: =IF($A37<=Вводные!$B9,Вводные!$B11*D37,0) -> 0 | F37: =Вводные!$B13*(1+Вводные!$B15)^((A37-1)/12) -> 216248.64 | G37: =E37*F37 -> 0 | H37: =IF(AND($A37>=MAX(1,Вводные!$B9-MIN(6,Вводные!$B9)+1),$A37<=Вводные!$B9),Вводные!$B12/MIN(6,Вводные!$B9),0) -> 0 | I37: =H37*Вводные!$B14 -> 0 | J37: =G37+I37 -> 0 | K37: =SUM($J$4:J37) -> 1.4741871e+09 | L37: =K37 -> 1.4741871e+09 | M37: =IF(AND(YEAR(B37)=YEAR(Вводные!$B$28),MONTH(B37)=MONTH(Вводные!$B$28)),L37,0) -> 0 | N37: =J37 -> 0 | O37: =IF(E37=0,0,G37/E37) -> 0 | P37: =IF(B37<Вводные!$B$28,0,IF(AND(YEAR(B37)=YEAR(Вводные!$B$28),MONTH(B37)=MONTH(Вводные!$B$28)),M37,J37)) -> 0
A38: 35 | B38: 47088 | C38: 0 | D38: =IF($A38<=Вводные!$B9,C38/SUMPRODUCT(($A$4:$A$39<=Вводные!$B9)*$C$4:$C$39),0) -> 0 | E38: =IF($A38<=Вводные!$B9,Вводные!$B11*D38,0) -> 0 | F38: =Вводные!$B13*(1+Вводные!$B15)^((A38-1)/12) -> 217639.99 | G38: =E38*F38 -> 0 | H38: =IF(AND($A38>=MAX(1,Вводные!$B9-MIN(6,Вводные!$B9)+1),$A38<=Вводные!$B9),Вводные!$B12/MIN(6,Вводные!$B9),0) -> 0 | I38: =H38*Вводные!$B14 -> 0 | J38: =G38+I38 -> 0 | K38: =SUM($J$4:J38) -> 1.4741871e+09 | L38: =K38 -> 1.4741871e+09 | M38: =IF(AND(YEAR(B38)=YEAR(Вводные!$B$28),MONTH(B38)=MONTH(Вводные!$B$28)),L38,0) -> 0 | N38: =J38 -> 0 | O38: =IF(E38=0,0,G38/E38) -> 0 | P38: =IF(B38<Вводные!$B$28,0,IF(AND(YEAR(B38)=YEAR(Вводные!$B$28),MONTH(B38)=MONTH(Вводные!$B$28)),M38,J38)) -> 0
A39: 36 | B39: 47119 | C39: 0 | D39: =IF($A39<=Вводные!$B9,C39/SUMPRODUCT(($A$4:$A$39<=Вводные!$B9)*$C$4:$C$39),0) -> 0 | E39: =IF($A39<=Вводные!$B9,Вводные!$B11*D39,0) -> 0 | F39: =Вводные!$B13*(1+Вводные!$B15)^((A39-1)/12) -> 219040.29 | G39: =E39*F39 -> 0 | H39: =IF(AND($A39>=MAX(1,Вводные!$B9-MIN(6,Вводные!$B9)+1),$A39<=Вводные!$B9),Вводные!$B12/MIN(6,Вводные!$B9),0) -> 0 | I39: =H39*Вводные!$B14 -> 0 | J39: =G39+I39 -> 0 | K39: =SUM($J$4:J39) -> 1.4741871e+09 | L39: =K39 -> 1.4741871e+09 | M39: =IF(AND(YEAR(B39)=YEAR(Вводные!$B$28),MONTH(B39)=MONTH(Вводные!$B$28)),L39,0) -> 0 | N39: =J39 -> 0 | O39: =IF(E39=0,0,G39/E39) -> 0 | P39: =IF(B39<Вводные!$B$28,0,IF(AND(YEAR(B39)=YEAR(Вводные!$B$28),MONTH(B39)=MONTH(Вводные!$B$28)),M39,J39)) -> 0
A41: ИТОГО | E41: =SUM(E4:E39) -> 7860.32 | J41: =SUM(J4:J39) -> 1.4741871e+09 | K41: =MAX(K4:K39) -> 1.4741871e+09 | L41: =MAX(L4:L39) -> 1.4741871e+09 | N41: =SUM(N4:N39) -> 1.4741871e+09

Sheet Кредит
A1: КРЕДИТ И ПРОЦЕНТЫ
A3: Месяц | B3: Дата | C3: Лимит периода | D3: CAPEX | E3: Коммерч. расходы | F3: Всего затрат | G3: Собств. средства | H3: Потребность в кредите | I3: Выборка | J3: Долг на начало | K3: Эскроу накопленно | L3: Коэфф. покрытия | M3: Ставка, годовая | N3: Начисленные проценты | O3: Капитализация процентов | P3: Проценты к оплате | Q3: Комиссия за лимит | R3: Погашение основного долга | S3: Долг на конец | T3: Комментарий | V3: Ключевые метрики
A4: 1 | B4: 46054 | C4: =IF(B4<=DATE(2026,3,31),159641000,IF(B4<=DATE(2026,12,31),545820000,IF(B4<=DATE(2027,6,30),797820000,IF(B4<=DATE(2028,3,31),1084000000,1084000000)))) -> 159641000 | D4: =ГПР!F16 -> 14148576 | E4: =ГПР!F14 -> 7074288 | F4: =IF(A4<=Вводные!$B9,Структура_затрат!$H$35/Вводные!$B9,0) -> 2764100.8 | G4: =(E4+F4)*Вводные!$B18 -> 1478709.8 | H4: =MAX(0,E4+F4-G4) -> 8359679 | I4: =MIN(H4,MAX(0,C4-J4)) -> 8359679 | J4: =IF(A4=1,0,S3) -> 0 | K4: =Продажи!L4 -> 26453000 | L4: =IF((J4+I4)=0,0,K4/(J4+I4)) -> 3.164356 | M4: =IF(L4>1.3,Вводные!$B26,IF(L4>1.2,Вводные!$B25,IF(L4>1.1,Вводные!$B24,IF(L4>=1,Вводные!$B23,Вводные!$B21+Вводные!$B22)))) -> 0.0001 | N4: =(J4+I4)*M4/12 -> 69.663991 | O4: =IF(B4<=Вводные!$B27,N4,0) -> 69.663991 | P4: =IF(B4<=Вводные!$B27,0,N4) -> 0 | Q4: =MAX(0,(C4-(J4+I4)))*Вводные!$B20/12 -> 36559.653 | R4: =IF(OR(YEAR(B4)>YEAR(Вводные!$B28),AND(YEAR(B4)=YEAR(Вводные!$B28),MONTH(B4)>=MONTH(Вводные!$B28))),MAX(0,MIN(J4+I4+O4+Q4,Продажи!N4-P4-Q4)),0) -> 0 | S4: =J4+I4+O4+Q4-R4 -> 8396308.3 | T4: =IF(S4=0,"Кредит погашен",IF(L4<1,"Низкое покрытие","Рабочий режим")) -> Рабочий режим | V4: Пик долга | W4: =MAX(S4:S39) -> 7.4105582e+08
A5: 2 | B5: 46082 | C5: =IF(B5<=DATE(2026,3,31),159641000,IF(B5<=DATE(2026,12,31),545820000,IF(B5<=DATE(2027,6,30),797820000,IF(B5<=DATE(2028,3,31),1084000000,1084000000)))) -> 159641000 | D5: =ГПР!G16 -> 33580116 | E5: =ГПР!G14 -> 16790058 | F5: =IF(A5<=Вводные!$B9,Структура_затрат!$H$35/Вводные!$B9,0) -> 2764100.8 | G5: =(E5+F5)*Вводные!$B18 -> 2938990.1 | H5: =MAX(0,E5+F5-G5) -> 16615169 | I5: =MIN(H5,MAX(0,C5-J5)) -> 16615169 | J5: =IF(A5=1,0,S4) -> 8396308.3 | K5: =Продажи!L5 -> 53076199 | L5: =IF((J5+I5)=0,0,K5/(J5+I5)) -> 2.1220738 | M5: =IF(L5>1.3,Вводные!$B26,IF(L5>1.2,Вводные!$B25,IF(L5>1.1,Вводные!$B24,IF(L5>=1,Вводные!$B23,Вводные!$B21+Вводные!$B22)))) -> 0.0001 | N5: =(J5+I5)*M5/12 -> 208.42898 | O5: =IF(B5<=Вводные!$B27,N5,0) -> 208.42898 | P5: =IF(B5<=Вводные!$B27,0,N5) -> 0 | Q5: =MAX(0,(C5-(J5+I5)))*Вводные!$B20/12 -> 32535.468 | R5: =IF(OR(YEAR(B5)>YEAR(Вводные!$B28),AND(YEAR(B5)=YEAR(Вводные!$B28),MONTH(B5)>=MONTH(Вводные!$B28))),MAX(0,MIN(J5+I5+O5+Q5,Продажи!N5-P5-Q5)),0) -> 0 | S5: =J5+I5+O5+Q5-R5 -> 25044221 | T5: =IF(S5=0,"Кредит погашен",IF(L5<1,"Низкое покрытие","Рабочий режим")) -> Рабочий режим | V5: Капитализированные % | W5: =SUM(O4:O39) -> 324945.55
A6: 3 | B6: 46113 | C6: =IF(B6<=DATE(2026,3,31),159641000,IF(B6<=DATE(2026,12,31),545820000,IF(B6<=DATE(2027,6,30),797820000,IF(B6<=DATE(2028,3,31),1084000000,1084000000)))) -> 545820000 | D6: =ГПР!H16 -> 74487570 | E6: =ГПР!H14 -> 37243785 | F6: =IF(A6<=Вводные!$B9,Структура_затрат!$H$35/Вводные!$B9,0) -> 2764100.8 | G6: =(E6+F6)*Вводные!$B18 -> 6013185.2 | H6: =MAX(0,E6+F6-G6) -> 33994701 | I6: =MIN(H6,MAX(0,C6-J6)) -> 33994701 | J6: =IF(A6=1,0,S5) -> 25044221 | K6: =Продажи!L6 -> 79870693 | L6: =IF((J6+I6)=0,0,K6/(J6+I6)) -> 1.3528481 | M6: =IF(L6>1.3,Вводные!$B26,IF(L6>1.2,Вводные!$B25,IF(L6>1.1,Вводные!$B24,IF(L6>=1,Вводные!$B23,Вводные!$B21+Вводные!$B22)))) -> 0.0001 | N6: =(J6+I6)*M6/12 -> 491.99101 | O6: =IF(B6<=Вводные!$B27,N6,0) -> 491.99101 | P6: =IF(B6<=Вводные!$B27,0,N6) -> 0 | Q6: =MAX(0,(C6-(J6+I6)))*Вводные!$B20/12 -> 117638.76 | R6: =IF(OR(YEAR(B6)>YEAR(Вводные!$B28),AND(YEAR(B6)=YEAR(Вводные!$B28),MONTH(B6)>=MONTH(Вводные!$B28))),MAX(0,MIN(J6+I6+O6+Q6,Продажи!N6-P6-Q6)),0) -> 0 | S6: =J6+I6+O6+Q6-R6 -> 59157052 | T6: =IF(S6=0,"Кредит погашен",IF(L6<1,"Низкое покрытие","Рабочий режим")) -> Рабочий режим | V6: Проценты к оплате | W6: =SUM(P4:P39) -> 111040.08
A7: 4 | B7: 46143 | C7: =IF(B7<=DATE(2026,3,31),159641000,IF(B7<=DATE(2026,12,31),545820000,IF(B7<=DATE(2027,6,30),797820000,IF(B7<=DATE(2028,3,31),1084000000,1084000000)))) -> 545820000 | D7: =ГПР!I16 -> 55056030 | E7: =ГПР!I14 -> 27528015 | F7: =IF(A7<=Вводные!$B9,Структура_затрат!$H$35/Вводные!$B9,0) -> 2764100.8 | G7: =(E7+F7)*Вводные!$B18 -> 4552905 | H7: =MAX(0,E7+F7-G7) -> 25739211 | I7: =MIN(H7,MAX(0,C7-J7)) -> 25739211 | J7: =IF(A7=1,0,S6) -> 59157052 | K7: =Продажи!L7 -> 1.0683758e+08 | L7: =IF((J7+I7)=0,0,K7/(J7+I7)) -> 1.2584486 | M7: =IF(L7>1.3,Вводные!$B26,IF(L7>1.2,Вводные!$B25,IF(L7>1.1,Вводные!$B24,IF(L7>=1,Вводные!$B23,Вводные!$B21+Вводные!$B22)))) -> 0.0151 | N7: =(J7+I7)*M7/12 -> 106827.8 | O7: =IF(B7<=Вводные!$B27,N7,0) -> 106827.8 | P7: =IF(B7<=Вводные!$B27,0,N7) -> 0 | Q7: =MAX(0,(C7-(J7+I7)))*Вводные!$B20/12 -> 111389.9 | R7: =IF(OR(YEAR(B7)>YEAR(Вводные!$B28),AND(YEAR(B7)=YEAR(Вводные!$B28),MONTH(B7)>=MONTH(Вводные!$B28))),MAX(0,MIN(J7+I7+O7+Q7,Продажи!N7-P7-Q7)),0) -> 0 | S7: =J7+I7+O7+Q7-R7 -> 85114481 | T7: =IF(S7=0,"Кредит погашен",IF(L7<1,"Низкое покрытие","Рабочий режим")) -> Рабочий режим | V7: Комиссия | W7: =SUM(Q4:Q39) -> 2586099.3
A8: 5 | B8: 46174 | C8: =IF(B8<=DATE(2026,3,31),159641000,IF(B8<=DATE(2026,12,31),545820000,IF(B8<=DATE(2027,6,30),797820000,IF(B8<=DATE(2028,3,31),1084000000,1084000000)))) -> 545820000 | D8: =ГПР!J16 -> 1.0279525e+08 | E8: =ГПР!J14 -> 51397623 | F8: =IF(A8<=Вводные!$B9,Структура_затрат!$H$35/Вводные!$B9,0) -> 2764100.8 | G8: =(E8+F8)*Вводные!$B18 -> 8140507.1 | H8: =MAX(0,E8+F8-G8) -> 46021217 | I8: =MIN(H8,MAX(0,C8-J8)) -> 46021217 | J8: =IF(A8=1,0,S7) -> 85114481 | K8: =Продажи!L8 -> 1.6111838e+08 | L8: =IF((J8+I8)=0,0,K8/(J8+I8)) -> 1.2286386 | M8: =IF(L8>1.3,Вводные!$B26,IF(L8>1.2,Вводные!$B25,IF(L8>1.1,Вводные!$B24,IF(L8>=1,Вводные!$B23,Вводные!$B21+Вводные!$B22)))) -> 0.0151 | N8: =(J8+I8)*M8/12 -> 165012.42 | O8: =IF(B8<=Вводные!$B27,N8,0) -> 165012.42 | P8: =IF(B8<=Вводные!$B27,0,N8) -> 0 | Q8: =MAX(0,(C8-(J8+I8)))*Вводные!$B20/12 -> 100215.37 | R8: =IF(OR(YEAR(B8)>YEAR(Вводные!$B28),AND(YEAR(B8)=YEAR(Вводные!$B28),MONTH(B8)>=MONTH(Вводные!$B28))),MAX(0,MIN(J8+I8+O8+Q8,Продажи!N8-P8-Q8)),0) -> 0 | S8: =J8+I8+O8+Q8-R8 -> 1.3140093e+08 | T8: =IF(S8=0,"Кредит погашен",IF(L8<1,"Низкое покрытие","Рабочий режим")) -> Рабочий режим | V8: Остаток долга | W8: =S39 -> 7.4105582e+08
A9: 6 | B9: 46204 | C9: =IF(B9<=DATE(2026,3,31),159641000,IF(B9<=DATE(2026,12,31),545820000,IF(B9<=DATE(2027,6,30),797820000,IF(B9<=DATE(2028,3,31),1084000000,1084000000)))) -> 545820000 | D9: =ГПР!K16 -> 47739216 | E9: =ГПР!K14 -> 23869608 | F9: =IF(A9<=Вводные!$B9,Структура_затрат!$H$35/Вводные!$B9,0) -> 2764100.8 | G9: =(E9+F9)*Вводные!$B18 -> 4003046.4 | H9: =MAX(0,E9+F9-G9) -> 22630662 | I9: =MIN(H9,MAX(0,C9-J9)) -> 22630662 | J9: =IF(A9=1,0,S8) -> 1.3140093e+08 | K9: =Продажи!L9 -> 2.1574841e+08 | L9: =IF((J9+I9)=0,0,K9/(J9+I9)) -> 1.4006764 | M9: =IF(L9>1.3,Вводные!$B26,IF(L9>1.2,Вводные!$B25,IF(L9>1.1,Вводные!$B24,IF(L9>=1,Вводные!$B23,Вводные!$B21+Вводные!$B22)))) -> 0.0001 | N9: =(J9+I9)*M9/12 -> 1283.5966 | O9: =IF(B9<=Вводные!$B27,N9,0) -> 1283.5966 | P9: =IF(B9<=Вводные!$B27,0,N9) -> 0 | Q9: =MAX(0,(C9-(J9+I9)))*Вводные!$B20/12 -> 94682.2 | R9: =IF(OR(YEAR(B9)>YEAR(Вводные!$B28),AND(YEAR(B9)=YEAR(Вводные!$B28),MONTH(B9)>=MONTH(Вводные!$B28))),MAX(0,MIN(J9+I9+O9+Q9,Продажи!N9-P9-Q9)),0) -> 0 | S9: =J9+I9+O9+Q9-R9 -> 1.5412755e+08 | T9: =IF(S9=0,"Кредит погашен",IF(L9<1,"Низкое покрытие","Рабочий режим")) -> Рабочий режим
A10: 7 | B10: 46235 | C10: =IF(B10<=DATE(2026,3,31),159641000,IF(B10<=DATE(2026,12,31),545820000,IF(B10<=DATE(2027,6,30),797820000,IF(B10<=DATE(2028,3,31),1084000000,1084000000)))) -> 545820000 | D10: =ГПР!L16 -> 47739216 | E10: =ГПР!L14 -> 23869608 | F10: =IF(A10<=Вводные!$B9,Структура_затрат!$H$35/Вводные!$B9,0) -> 2764100.8 | G10: =(E10+F10)*Вводные!$B18 -> 4003046.4 | H10: =MAX(0,E10+F10-G10) -> 22630662 | I10: =MIN(H10,MAX(0,C10-J10)) -> 22630662 | J10: =IF(A10=1,0,S9) -> 1.5412755e+08 | K10: =Продажи!L10 -> 2.982207e+08 | L10: =IF((J10+I10)=0,0,K10/(J10+I10)) -> 1.6871674 | M10: =IF(L10>1.3,Вводные!$B26,IF(L10>1.2,Вводные!$B25,IF(L10>1.1,Вводные!$B24,IF(L10>=1,Вводные!$B23,Вводные!$B21+Вводные!$B22)))) -> 0.0001 | N10: =(J10+I10)*M10/12 -> 1472.9851 | O10: =IF(B10<=Вводные!$B27,N10,0) -> 1472.9851 | P10: =IF(B10<=Вводные!$B27,0,N10) -> 0 | Q10: =MAX(0,(C10-(J10+I10)))*Вводные!$B20/12 -> 89189.931 | R10: =IF(OR(YEAR(B10)>YEAR(Вводные!$B28),AND(YEAR(B10)=YEAR(Вводные!$B28),MONTH(B10)>=MONTH(Вводные!$B28))),MAX(0,MIN(J10+I10+O10+Q10,Продажи!N10-P10-Q10)),0) -> 0 | S10: =J10+I10+O10+Q10-R10 -> 1.7684888e+08 | T10: =IF(S10=0,"Кредит погашен",IF(L10<1,"Низкое покрытие","Рабочий режим")) -> Рабочий режим
A11: 8 | B11: 46266 | C11: =IF(B11<=DATE(2026,3,31),159641000,IF(B11<=DATE(2026,12,31),545820000,IF(B11<=DATE(2027,6,30),797820000,IF(B11<=DATE(2028,3,31),1084000000,1084000000)))) -> 545820000 | D11: =ГПР!M16 -> 47739216 | E11: =ГПР!M14 -> 23869608 | F11: =IF(A11<=Вводные!$B9,Структура_затрат!$H$35/Вводные!$B9,0) -> 2764100.8 | G11: =(E11+F11)*Вводные!$B18 -> 4003046.4 | H11: =MAX(0,E11+F11-G11) -> 22630662 | I11: =MIN(H11,MAX(0,C11-J11)) -> 22630662 | J11: =IF(A11=1,0,S10) -> 1.7684888e+08 | K11: =Продажи!L11 -> 3.8122363e+08 | L11: =IF((J11+I11)=0,0,K11/(J11+I11)) -> 1.9110914 | M11: =IF(L11>1.3,Вводные!$B26,IF(L11>1.2,Вводные!$B25,IF(L11>1.1,Вводные!$B24,IF(L11>=1,Вводные!$B23,Вводные!$B21+Вводные!$B22)))) -> 0.0001 | N11: =(J11+I11)*M11/12 -> 1662.3295 | O11: =IF(B11<=Вводные!$B27,N11,0) -> 1662.3295 | P11: =IF(B11<=Вводные!$B27,0,N11) -> 0 | Q11: =MAX(0,(C11-(J11+I11)))*Вводные!$B20/12 -> 83698.944 | R11: =IF(OR(YEAR(B11)>YEAR(Вводные!$B28),AND(YEAR(B11)=YEAR(Вводные!$B28),MONTH(B11)>=MONTH(Вводные!$B28))),MAX(0,MIN(J11+I11+O11+Q11,Продажи!N11-P11-Q11)),0) -> 0 | S11: =J11+I11+O11+Q11-R11 -> 1.995649e+08 | T11: =IF(S11=0,"Кредит погашен",IF(L11<1,"Низкое покрытие","Рабочий режим")) -> Рабочий режим
A12: 9 | B12: 46296 | C12: =IF(B12<=DATE(2026,3,31),159641000,IF(B12<=DATE(2026,12,31),545820000,IF(B12<=DATE(2027,6,30),797820000,IF(B12<=DATE(2028,3,31),1084000000,1084000000)))) -> 545820000 | D12: =ГПР!N16 -> 1.6257036e+08 | E12: =ГПР!N14 -> 81285182 | F12: =IF(A12<=Вводные!$B9,Структура_затрат!$H$35/Вводные!$B9,0) -> 2764100.8 | G12: =(E12+F12)*Вводные!$B18 -> 12632607 | H12: =MAX(0,E12+F12-G12) -> 71416676 | I12: =MIN(H12,MAX(0,C12-J12)) -> 71416676 | J12: =IF(A12=1,0,S11) -> 1.995649e+08 | K12: =Продажи!L12 -> 4.9260625e+08 | L12: =IF((J12+I12)=0,0,K12/(J12+I12)) -> 1.8178588 | M12: =IF(L12>1.3,Вводные!$B26,IF(L12>1.2,Вводные!$B25,IF(L12>1.1,Вводные!$B24,IF(L12>=1,Вводные!$B23,Вводные!$B21+Вводные!$B22)))) -> 0.0001 | N12: =(J12+I12)*M12/12 -> 2258.1798 | O12: =IF(B12<=Вводные!$B27,N12,0) -> 2258.1798 | P12: =IF(B12<=Вводные!$B27,0,N12) -> 0 | Q12: =MAX(0,(C12-(J12+I12)))*Вводные!$B20/12 -> 66419.286 | R12: =IF(OR(YEAR(B12)>YEAR(Вводные!$B28),AND(YEAR(B12)=YEAR(Вводные!$B28),MONTH(B12)>=MONTH(Вводные!$B28))),MAX(0,MIN(J12+I12+O12+Q12,Продажи!N12-P12-Q12)),0) -> 0 | S12: =J12+I12+O12+Q12-R12 -> 2.7105025e+08 | T12: =IF(S12=0,"Кредит погашен",IF(L12<1,"Низкое покрытие","Рабочий режим")) -> Рабочий режим
A13: 10 | B13: 46327 | C13: =IF(B13<=DATE(2026,3,31),159641000,IF(B13<=DATE(2026,12,31),545820000,IF(B13<=DATE(2027,6,30),797820000,IF(B13<=DATE(2028,3,31),1084000000,1084000000)))) -> 545820000 | D13: =ГПР!O16 -> 1.7197655e+08 | E13: =ГПР!O14 -> 85988273 | F13: =IF(A13<=Вводные!$B9,Структура_затрат!$H$35/Вводные!$B9,0) -> 2764100.8 | G13: =(E13+F13)*Вводные!$B18 -> 13339482 | H13: =MAX(0,E13+F13-G13) -> 75412892 | I13: =MIN(H13,MAX(0,C13-J13)) -> 75412892 | J13: =IF(A13=1,0,S12) -> 2.7105025e+08 | K13: =Продажи!L13 -> 6.047055e+08 | L13: =IF((J13+I13)=0,0,K13/(J13+I13)) -> 1.7453675 | M13: =IF(L13>1.3,Вводные!$B26,IF(L13>1.2,Вводные!$B25,IF(L13>1.1,Вводные!$B24,IF(L13>=1,Вводные!$B23,Вводные!$B21+Вводные!$B22)))) -> 0.0001 | N13: =(J13+I13)*M13/12 -> 2887.1929 | O13: =IF(B13<=Вводные!$B27,N13,0) -> 2887.1929 | P13: =IF(B13<=Вводные!$B27,0,N13) -> 0 | Q13: =MAX(0,(C13-(J13+I13)))*Вводные!$B20/12 -> 48177.906 | R13: =IF(OR(YEAR(B13)>YEAR(Вводные!$B28),AND(YEAR(B13)=YEAR(Вводные!$B28),MONTH(B13)>=MONTH(Вводные!$B28))),MAX(0,MIN(J13+I13+O13+Q13,Продажи!N13-P13-Q13)),0) -> 0 | S13: =J13+I13+O13+Q13-R13 -> 3.4651421e+08 | T13: =IF(S13=0,"Кредит погашен",IF(L13<1,"Низкое покрытие","Рабочий режим")) -> Рабочий режим
A14: 11 | B14: 46357 | C14: =IF(B14<=DATE(2026,3,31),159641000,IF(B14<=DATE(2026,12,31),545820000,IF(B14<=DATE(2027,6,30),797820000,IF(B14<=DATE(2028,3,31),1084000000,1084000000)))) -> 545820000 | D14: =ГПР!P16 -> 1.9374707e+08 | E14: =ГПР!P14 -> 96873534 | F14: =IF(A14<=Вводные!$B9,Структура_затрат!$H$35/Вводные!$B9,0) -> 2764100.8 | G14: =(E14+F14)*Вводные!$B18 -> 14975537 | H14: =MAX(0,E14+F14-G14) -> 84662098 | I14: =MIN(H14,MAX(0,C14-J14)) -> 84662098 | J14: =IF(A14=1,0,S13) -> 3.4651421e+08 | K14: =Продажи!L14 -> 7.4733114e+08 | L14: =IF((J14+I14)=0,0,K14/(J14+I14)) -> 1.7332379 | M14: =IF(L14>1.3,Вводные!$B26,IF(L14>1.2,Вводные!$B25,IF(L14>1.1,Вводные!$B24,IF(L14>=1,Вводные!$B23,Вводные!$B21+Вводные!$B22)))) -> 0.0001 | N14: =(J14+I14)*M14/12 -> 3593.1359 | O14: =IF(B14<=Вводные!$B27,N14,0) -> 3593.1359 | P14: =IF(B14<=Вводные!$B27,0,N14) -> 0 | Q14: =MAX(0,(C14-(J14+I14)))*Вводные!$B20/12 -> 27705.558 | R14: =IF(OR(YEAR(B14)>YEAR(Вводные!$B28),AND(YEAR(B14)=YEAR(Вводные!$B28),MONTH(B14)>=MONTH(Вводные!$B28))),MAX(0,MIN(J14+I14+O14+Q14,Продажи!N14-P14-Q14)),0) -> 0 | S14: =J14+I14+O14+Q14-R14 -> 4.3120761e+08 | T14: =IF(S14=0,"Кредит погашен",IF(L14<1,"Низкое покрытие","Рабочий режим")) -> Рабочий режим
A15: 12 | B15: 46388 | C15: =IF(B15<=DATE(2026,3,31),159641000,IF(B15<=DATE(2026,12,31),545820000,IF(B15<=DATE(2027,6,30),797820000,IF(B15<=DATE(2028,3,31),1084000000,1084000000)))) -> 797820000 | D15: =ГПР!Q16 -> 1.9374707e+08 | E15: =ГПР!Q14 -> 96873534 | F15: =IF(A15<=Вводные!$B9,Структура_затрат!$H$35/Вводные!$B9,0) -> 2764100.8 | G15: =(E15+F15)*Вводные!$B18 -> 14975537 | H15: =MAX(0,E15+F15-G15) -> 84662098 | I15: =MIN(H15,MAX(0,C15-J15)) -> 84662098 | J15: =IF(A15=1,0,S14) -> 4.3120761e+08 | K15: =Продажи!L15 -> 8.9086414e+08 | L15: =IF((J15+I15)=0,0,K15/(J15+I15)) -> 1.7269169 | M15: =IF(L15>1.3,Вводные!$B26,IF(L15>1.2,Вводные!$B25,IF(L15>1.1,Вводные!$B24,IF(L15>=1,Вводные!$B23,Вводные!$B21+Вводные!$B22)))) -> 0.0001 | N15: =(J15+I15)*M15/12 -> 4298.9142 | O15: =IF(B15<=Вводные!$B27,N15,0) -> 4298.9142 | P15: =IF(B15<=Вводные!$B27,0,N15) -> 0 | Q15: =MAX(0,(C15-(J15+I15)))*Вводные!$B20/12 -> 68137.987 | R15: =IF(OR(YEAR(B15)>YEAR(Вводные!$B28),AND(YEAR(B15)=YEAR(Вводные!$B28),MONTH(B15)>=MONTH(Вводные!$B28))),MAX(0,MIN(J15+I15+O15+Q15,Продажи!N15-P15-Q15)),0) -> 0 | S15: =J15+I15+O15+Q15-R15 -> 5.1594214e+08 | T15: =IF(S15=0,"Кредит погашен",IF(L15<1,"Низкое покрытие","Рабочий режим")) -> Рабочий режим
A16: 13 | B16: 46419 | C16: =IF(B16<=DATE(2026,3,31),159641000,IF(B16<=DATE(2026,12,31),545820000,IF(B16<=DATE(2027,6,30),797820000,IF(B16<=DATE(2028,3,31),1084000000,1084000000)))) -> 797820000 | D16: =ГПР!R16 -> 1.9374707e+08 | E16: =ГПР!R14 -> 96873534 | F16: =IF(A16<=Вводные!$B9,Структура_затрат!$H$35/Вводные!$B9,0) -> 2764100.8 | G16: =(E16+F16)*Вводные!$B18 -> 14975537 | H16: =MAX(0,E16+F16-G16) -> 84662098 | I16: =MIN(H16,MAX(0,C16-J16)) -> 84662098 | J16: =IF(A16=1,0,S15) -> 5.1594214e+08 | K16: =Продажи!L16 -> 1.0353103e+09 | L16: =IF((J16+I16)=0,0,K16/(J16+I16)) -> 1.7237813 | M16: =IF(L16>1.3,Вводные!$B26,IF(L16>1.2,Вводные!$B25,IF(L16>1.1,Вводные!$B24,IF(L16>=1,Вводные!$B23,Вводные!$B21+Вводные!$B22)))) -> 0.0001 | N16: =(J16+I16)*M16/12 -> 5005.0354 | O16: =IF(B16<=Вводные!$B27,N16,0) -> 5005.0354 | P16: =IF(B16<=Вводные!$B27,0,N16) -> 0 | Q16: =MAX(0,(C16-(J16+I16)))*Вводные!$B20/12 -> 47660.475 | R16: =IF(OR(YEAR(B16)>YEAR(Вводные!$B28),AND(YEAR(B16)=YEAR(Вводные!$B28),MONTH(B16)>=MONTH(Вводные!$B28))),MAX(0,MIN(J16+I16+O16+Q16,Продажи!N16-P16-Q16)),0) -> 0 | S16: =J16+I16+O16+Q16-R16 -> 6.0065691e+08 | T16: =IF(S16=0,"Кредит погашен",IF(L16<1,"Низкое покрытие","Рабочий режим")) -> Рабочий режим
A17: 14 | B17: 46447 | C17: =IF(B17<=DATE(2026,3,31),159641000,IF(B17<=DATE(2026,12,31),545820000,IF(B17<=DATE(2027,6,30),797820000,IF(B17<=DATE(2028,3,31),1084000000,1084000000)))) -> 797820000 | D17: =ГПР!S16 -> 1.4600785e+08 | E17: =ГПР!S14 -> 73003926 | F17: =IF(A17<=Вводные!$B9,Структура_затрат!$H$35/Вводные!$B9,0) -> 2764100.8 | G17: =(E17+F17)*Вводные!$B18 -> 11387934 | H17: =MAX(0,E17+F17-G17) -> 64380093 | I17: =MIN(H17,MAX(0,C17-J17)) -> 64380093 | J17: =IF(A17=1,0,S16) -> 6.0065691e+08 | K17: =Продажи!L17 -> 1.1806756e+09 | L17: =IF((J17+I17)=0,0,K17/(J17+I17)) -> 1.7753533 | M17: =IF(L17>1.3,Вводные!$B26,IF(L17>1.2,Вводные!$B25,IF(L17>1.1,Вводные!$B24,IF(L17>=1,Вводные!$B23,Вводные!$B21+Вводные!$B22)))) -> 0.0001 | N17: =(J17+I17)*M17/12 -> 5541.975 | O17: =IF(B17<=Вводные!$B27,N17,0) -> 5541.975 | P17: =IF(B17<=Вводные!$B27,0,N17) -> 0 | Q17: =MAX(0,(C17-(J17+I17)))*Вводные!$B20/12 -> 32089.225 | R17: =IF(OR(YEAR(B17)>YEAR(Вводные!$B28),AND(YEAR(B17)=YEAR(Вводные!$B28),MONTH(B17)>=MONTH(Вводные!$B28))),MAX(0,MIN(J17+I17+O17+Q17,Продажи!N17-P17-Q17)),0) -> 0 | S17: =J17+I17+O17+Q17-R17 -> 6.6507463e+08 | T17: =IF(S17=0,"Кредит погашен",IF(L17<1,"Низкое покрытие","Рабочий режим")) -> Рабочий режим
A18: 15 | B18: 46478 | C18: =IF(B18<=DATE(2026,3,31),159641000,IF(B18<=DATE(2026,12,31),545820000,IF(B18<=DATE(2027,6,30),797820000,IF(B18<=DATE(2028,3,31),1084000000,1084000000)))) -> 797820000 | D18: =ГПР!T16 -> 1.0081153e+08 | E18: =ГПР!T14 -> 50405765 | F18: =IF(A18<=Вводные!$B9,Структура_затрат!$H$35/Вводные!$B9,0) -> 2764100.8 | G18: =(E18+F18)*Вводные!$B18 -> 7991430.8 | H18: =MAX(0,E18+F18-G18) -> 45178435 | I18: =MIN(H18,MAX(0,C18-J18)) -> 45178435 | J18: =IF(A18=1,0,S17) -> 6.6507463e+08 | K18: =Продажи!L18 -> 1.3269659e+09 | L18: =IF((J18+I18)=0,0,K18/(J18+I18)) -> 1.8683001 | M18: =IF(L18>1.3,Вводные!$B26,IF(L18>1.2,Вводные!$B25,IF(L18>1.1,Вводные!$B24,IF(L18>=1,Вводные!$B23,Вводные!$B21+Вводные!$B22)))) -> 0.0001 | N18: =(J18+I18)*M18/12 -> 5918.7756 | O18: =IF(B18<=Вводные!$B27,N18,0) -> 5918.7756 | P18: =IF(B18<=Вводные!$B27,0,N18) -> 0 | Q18: =MAX(0,(C18-(J18+I18)))*Вводные!$B20/12 -> 21162.009 | R18: =IF(OR(YEAR(B18)>YEAR(Вводные!$B28),AND(YEAR(B18)=YEAR(Вводные!$B28),MONTH(B18)>=MONTH(Вводные!$B28))),MAX(0,MIN(J18+I18+O18+Q18,Продажи!N18-P18-Q18)),0) -> 0 | S18: =J18+I18+O18+Q18-R18 -> 7.1028015e+08 | T18: =IF(S18=0,"Кредит погашен",IF(L18<1,"Низкое покрытие","Рабочий режим")) -> Рабочий режим
A19: 16 | B19: 46508 | C19: =IF(B19<=DATE(2026,3,31),159641000,IF(B19<=DATE(2026,12,31),545820000,IF(B19<=DATE(2027,6,30),797820000,IF(B19<=DATE(2028,3,31),1084000000,1084000000)))) -> 797820000 | D19: =ГПР!U16 -> 42425529 | E19: =ГПР!U14 -> 21212764 | F19: =IF(A19<=Вводные!$B9,Структура_затрат!$H$35/Вводные!$B9,0) -> 2764100.8 | G19: =(E19+F19)*Вводные!$B18 -> 3603722.9 | H19: =MAX(0,E19+F19-G19) -> 20373142 | I19: =MIN(H19,MAX(0,C19-J19)) -> 20373142 | J19: =IF(A19=1,0,S18) -> 7.1028015e+08 | K19: =Продажи!L19 -> 1.4741871e+09 | L19: =IF((J19+I19)=0,0,K19/(J19+I19)) -> 2.0176288 | M19: =IF(L19>1.3,Вводные!$B26,IF(L19>1.2,Вводные!$B25,IF(L19>1.1,Вводные!$B24,IF(L19>=1,Вводные!$B23,Вводные!$B21+Вводные!$B22)))) -> 0.0001 | N19: =(J19+I19)*M19/12 -> 6088.7774 | O19: =IF(B19<=Вводные!$B27,N19,0) -> 6088.7774 | P19: =IF(B19<=Вводные!$B27,0,N19) -> 0 | Q19: =MAX(0,(C19-(J19+I19)))*Вводные!$B20/12 -> 16231.955 | R19: =IF(OR(YEAR(B19)>YEAR(Вводные!$B28),AND(YEAR(B19)=YEAR(Вводные!$B28),MONTH(B19)>=MONTH(Вводные!$B28))),MAX(0,MIN(J19+I19+O19+Q19,Продажи!N19-P19-Q19)),0) -> 0 | S19: =J19+I19+O19+Q19-R19 -> 7.3067561e+08 | T19: =IF(S19=0,"Кредит погашен",IF(L19<1,"Низкое покрытие","Рабочий режим")) -> Рабочий режим
A20: 17 | B20: 46539 | C20: =IF(B20<=DATE(2026,3,31),159641000,IF(B20<=DATE(2026,12,31),545820000,IF(B20<=DATE(2027,6,30),797820000,IF(B20<=DATE(2028,3,31),1084000000,1084000000)))) -> 797820000 | D20: =ГПР!V16 -> 20655007 | E20: =ГПР!V14 -> 10327504 | F20: =IF(A20<=Вводные!$B9,Структура_затрат!$H$35/Вводные!$B9,0) -> 0 | G20: =(E20+F20)*Вводные!$B18 -> 1552223.8 | H20: =MAX(0,E20+F20-G20) -> 8775279.9 | I20: =MIN(H20,MAX(0,C20-J20)) -> 8775279.9 | J20: =IF(A20=1,0,S19) -> 7.3067561e+08 | K20: =Продажи!L20 -> 1.4741871e+09 | L20: =IF((J20+I20)=0,0,K20/(J20+I20)) -> 1.9936241 | M20: =IF(L20>1.3,Вводные!$B26,IF(L20>1.2,Вводные!$B25,IF(L20>1.1,Вводные!$B24,IF(L20>=1,Вводные!$B23,Вводные!$B21+Вводные!$B22)))) -> 0.0001 | N20: =(J20+I20)*M20/12 -> 6162.0908 | O20: =IF(B20<=Вводные!$B27,N20,0) -> 6162.0908 | P20: =IF(B20<=Вводные!$B27,0,N20) -> 0 | Q20: =MAX(0,(C20-(J20+I20)))*Вводные!$B20/12 -> 14105.868 | R20: =IF(OR(YEAR(B20)>YEAR(Вводные!$B28),AND(YEAR(B20)=YEAR(Вводные!$B28),MONTH(B20)>=MONTH(Вводные!$B28))),MAX(0,MIN(J20+I20+O20+Q20,Продажи!N20-P20-Q20)),0) -> 0 | S20: =J20+I20+O20+Q20-R20 -> 7.3947116e+08 | T20: =IF(S20=0,"Кредит погашен",IF(L20<1,"Низкое покрытие","Рабочий режим")) -> Рабочий режим
A21: 18 | B21: 46569 | C21: =IF(B21<=DATE(2026,3,31),159641000,IF(B21<=DATE(2026,12,31),545820000,IF(B21<=DATE(2027,6,30),797820000,IF(B21<=DATE(2028,3,31),1084000000,1084000000)))) -> 1084000000 | D21: =ГПР!W16 -> 0 | E21: =ГПР!W14 -> 0 | F21: =IF(A21<=Вводные!$B9,Структура_затрат!$H$35/Вводные!$B9,0) -> 0 | G21: =(E21+F21)*Вводные!$B18 -> 0 | H21: =MAX(0,E21+F21-G21) -> 0 | I21: =MIN(H21,MAX(0,C21-J21)) -> 0 | J21: =IF(A21=1,0,S20) -> 7.3947116e+08 | K21: =Продажи!L21 -> 1.4741871e+09 | L21: =IF((J21+I21)=0,0,K21/(J21+I21)) -> 1.9935694 | M21: =IF(L21>1.3,Вводные!$B26,IF(L21>1.2,Вводные!$B25,IF(L21>1.1,Вводные!$B24,IF(L21>=1,Вводные!$B23,Вводные!$B21+Вводные!$B22)))) -> 0.0001 | N21: =(J21+I21)*M21/12 -> 6162.2597 | O21: =IF(B21<=Вводные!$B27,N21,0) -> 6162.2597 | P21: =IF(B21<=Вводные!$B27,0,N21) -> 0 | Q21: =MAX(0,(C21-(J21+I21)))*Вводные!$B20/12 -> 83261.137 | R21: =IF(OR(YEAR(B21)>YEAR(Вводные!$B28),AND(YEAR(B21)=YEAR(Вводные!$B28),MONTH(B21)>=MONTH(Вводные!$B28))),MAX(0,MIN(J21+I21+O21+Q21,Продажи!N21-P21-Q21)),0) -> 0 | S21: =J21+I21+O21+Q21-R21 -> 7.3956058e+08 | T21: =IF(S21=0,"Кредит погашен",IF(L21<1,"Низкое покрытие","Рабочий режим")) -> Рабочий режим
A22: 19 | B22: 46600 | C22: =IF(B22<=DATE(2026,3,31),159641000,IF(B22<=DATE(2026,12,31),545820000,IF(B22<=DATE(2027,6,30),797820000,IF(B22<=DATE(2028,3,31),1084000000,1084000000)))) -> 1084000000 | D22: =ГПР!X16 -> 0 | E22: =ГПР!X14 -> 0 | F22: =IF(A22<=Вводные!$B9,Структура_затрат!$H$35/Вводные!$B9,0) -> 0 | G22: =(E22+F22)*Вводные!$B18 -> 0 | H22: =MAX(0,E22+F22-G22) -> 0 | I22: =MIN(H22,MAX(0,C22-J22)) -> 0 | J22: =IF(A22=1,0,S21) -> 7.3956058e+08 | K22: =Продажи!L22 -> 1.4741871e+09 | L22: =IF((J22+I22)=0,0,K22/(J22+I22)) -> 1.9933284 | M22: =IF(L22>1.3,Вводные!$B26,IF(L22>1.2,Вводные!$B25,IF(L22>1.1,Вводные!$B24,IF(L22>=1,Вводные!$B23,Вводные!$B21+Вводные!$B22)))) -> 0.0001 | N22: =(J22+I22)*M22/12 -> 6163.0049 | O22: =IF(B22<=Вводные!$B27,N22,0) -> 0 | P22: =IF(B22<=Вводные!$B27,0,N22) -> 6163.0049 | Q22: =MAX(0,(C22-(J22+I22)))*Вводные!$B20/12 -> 83239.526 | R22: =IF(OR(YEAR(B22)>YEAR(Вводные!$B28),AND(YEAR(B22)=YEAR(Вводные!$B28),MONTH(B22)>=MONTH(Вводные!$B28))),MAX(0,MIN(J22+I22+O22+Q22,Продажи!N22-P22-Q22)),0) -> 0 | S22: =J22+I22+O22+Q22-R22 -> 7.3964382e+08 | T22: =IF(S22=0,"Кредит погашен",IF(L22<1,"Низкое покрытие","Рабочий режим")) -> Рабочий режим
A23: 20 | B23: 46631 | C23: =IF(B23<=DATE(2026,3,31),159641000,IF(B23<=DATE(2026,12,31),545820000,IF(B23<=DATE(2027,6,30),797820000,IF(B23<=DATE(2028,3,31),1084000000,1084000000)))) -> 1084000000 | D23: =ГПР!Y16 -> 0 | E23: =ГПР!Y14 -> 0 | F23: =IF(A23<=Вводные!$B9,Структура_затрат!$H$35/Вводные!$B9,0) -> 0 | G23: =(E23+F23)*Вводные!$B18 -> 0 | H23: =MAX(0,E23+F23-G23) -> 0 | I23: =MIN(H23,MAX(0,C23-J23)) -> 0 | J23: =IF(A23=1,0,S22) -> 7.3964382e+08 | K23: =Продажи!L23 -> 1.4741871e+09 | L23: =IF((J23+I23)=0,0,K23/(J23+I23)) -> 1.993104 | M23: =IF(L23>1.3,Вводные!$B26,IF(L23>1.2,Вводные!$B25,IF(L23>1.1,Вводные!$B24,IF(L23>=1,Вводные!$B23,Вводные!$B21+Вводные!$B22)))) -> 0.0001 | N23: =(J23+I23)*M23/12 -> 6163.6985 | O23: =IF(B23<=Вводные!$B27,N23,0) -> 0 | P23: =IF(B23<=Вводные!$B27,0,N23) -> 6163.6985 | Q23: =MAX(0,(C23-(J23+I23)))*Вводные!$B20/12 -> 83219.41 | R23: =IF(OR(YEAR(B23)>YEAR(Вводные!$B28),AND(YEAR(B23)=YEAR(Вводные!$B28),MONTH(B23)>=MONTH(Вводные!$B28))),MAX(0,MIN(J23+I23+O23+Q23,Продажи!N23-P23-Q23)),0) -> 0 | S23: =J23+I23+O23+Q23-R23 -> 7.3972704e+08 | T23: =IF(S23=0,"Кредит погашен",IF(L23<1,"Низкое покрытие","Рабочий режим")) -> Рабочий режим
A24: 21 | B24: 46661 | C24: =IF(B24<=DATE(2026,3,31),159641000,IF(B24<=DATE(2026,12,31),545820000,IF(B24<=DATE(2027,6,30),797820000,IF(B24<=DATE(2028,3,31),1084000000,1084000000)))) -> 1084000000 | D24: =ГПР!Z16 -> 0 | E24: =ГПР!Z14 -> 0 | F24: =IF(A24<=Вводные!$B9,Структура_затрат!$H$35/Вводные!$B9,0) -> 0 | G24: =(E24+F24)*Вводные!$B18 -> 0 | H24: =MAX(0,E24+F24-G24) -> 0 | I24: =MIN(H24,MAX(0,C24-J24)) -> 0 | J24: =IF(A24=1,0,S23) -> 7.3972704e+08 | K24: =Продажи!L24 -> 1.4741871e+09 | L24: =IF((J24+I24)=0,0,K24/(J24+I24)) -> 1.9928798 | M24: =IF(L24>1.3,Вводные!$B26,IF(L24>1.2,Вводные!$B25,IF(L24>1.1,Вводные!$B24,IF(L24>=1,Вводные!$B23,Вводные!$B21+Вводные!$B22)))) -> 0.0001 | N24: =(J24+I24)*M24/12 -> 6164.392 | O24: =IF(B24<=Вводные!$B27,N24,0) -> 0 | P24: =IF(B24<=Вводные!$B27,0,N24) -> 6164.392 | Q24: =MAX(0,(C24-(J24+I24)))*Вводные!$B20/12 -> 83199.298 | R24: =IF(OR(YEAR(B24)>YEAR(Вводные!$B28),AND(YEAR(B24)=YEAR(Вводные!$B28),MONTH(B24)>=MONTH(Вводные!$B28))),MAX(0,MIN(J24+I24+O24+Q24,Продажи!N24-P24-Q24)),0) -> 0 | S24: =J24+I24+O24+Q24-R24 -> 7.3981024e+08 | T24: =IF(S24=0,"Кредит погашен",IF(L24<1,"Низкое покрытие","Рабочий режим")) -> Рабочий режим
A25: 22 | B25: 46692 | C25: =IF(B25<=DATE(2026,3,31),159641000,IF(B25<=DATE(2026,12,31),545820000,IF(B25<=DATE(2027,6,30),797820000,IF(B25<=DATE(2028,3,31),1084000000,1084000000)))) -> 1084000000 | D25: =ГПР!AA16 -> 0 | E25: =ГПР!AA14 -> 0 | F25: =IF(A25<=Вводные!$B9,Структура_затрат!$H$35/Вводные!$B9,0) -> 0 | G25: =(E25+F25)*Вводные!$B18 -> 0 | H25: =MAX(0,E25+F25-G25) -> 0 | I25: =MIN(H25,MAX(0,C25-J25)) -> 0 | J25: =IF(A25=1,0,S24) -> 7.3981024e+08 | K25: =Продажи!L25 -> 1.4741871e+09 | L25: =IF((J25+I25)=0,0,K25/(J25+I25)) -> 1.9926557 | M25: =IF(L25>1.3,Вводные!$B26,IF(L25>1.2,Вводные!$B25,IF(L25>1.1,Вводные!$B24,IF(L25>=1,Вводные!$B23,Вводные!$B21+Вводные!$B22)))) -> 0.0001 | N25: =(J25+I25)*M25/12 -> 6165.0853 | O25: =IF(B25<=Вводные!$B27,N25,0) -> 0 | P25: =IF(B25<=Вводные!$B27,0,N25) -> 6165.0853 | Q25: =MAX(0,(C25-(J25+I25)))*Вводные!$B20/12 -> 83179.192 | R25: =IF(OR(YEAR(B25)>YEAR(Вводные!$B28),AND(YEAR(B25)=YEAR(Вводные!$B28),MONTH(B25)>=MONTH(Вводные!$B28))),MAX(0,MIN(J25+I25+O25+Q25,Продажи!N25-P25-Q25)),0) -> 0 | S25: =J25+I25+O25+Q25-R25 -> 7.3989342e+08 | T25: =IF(S25=0,"Кредит погашен",IF(L25<1,"Низкое покрытие","Рабочий режим")) -> Рабочий режим
A26: 23 | B26: 46722 | C26: =IF(B26<=DATE(2026,3,31),159641000,IF(B26<=DATE(2026,12,31),545820000,IF(B26<=DATE(2027,6,30),797820000,IF(B26<=DATE(2028,3,31),1084000000,1084000000)))) -> 1084000000 | D26: =ГПР!AB16 -> 0 | E26: =ГПР!AB14 -> 0 | F26: =IF(A26<=Вводные!$B9,Структура_затрат!$H$35/Вводные!$B9,0) -> 0 | G26: =(E26+F26)*Вводные!$B18 -> 0 | H26: =MAX(0,E26+F26-G26) -> 0 | I26: =MIN(H26,MAX(0,C26-J26)) -> 0 | J26: =IF(A26=1,0,S25) -> 7.3989342e+08 | K26: =Продажи!L26 -> 1.4741871e+09 | L26: =IF((J26+I26)=0,0,K26/(J26+I26)) -> 1.9924317 | M26: =IF(L26>1.3,Вводные!$B26,IF(L26>1.2,Вводные!$B25,IF(L26>1.1,Вводные!$B24,IF(L26>=1,Вводные!$B23,Вводные!$B21+Вводные!$B22)))) -> 0.0001 | N26: =(J26+I26)*M26/12 -> 6165.7785 | O26: =IF(B26<=Вводные!$B27,N26,0) -> 0 | P26: =IF(B26<=Вводные!$B27,0,N26) -> 6165.7785 | Q26: =MAX(0,(C26-(J26+I26)))*Вводные!$B20/12 -> 83159.09 | R26: =IF(OR(YEAR(B26)>YEAR(Вводные!$B28),AND(YEAR(B26)=YEAR(Вводные!$B28),MONTH(B26)>=MONTH(Вводные!$B28))),MAX(0,MIN(J26+I26+O26+Q26,Продажи!N26-P26-Q26)),0) -> 0 | S26: =J26+I26+O26+Q26-R26 -> 7.3997658e+08 | T26: =IF(S26=0,"Кредит погашен",IF(L26<1,"Низкое покрытие","Рабочий режим")) -> Рабочий режим
A27: 24 | B27: 46753 | C27: =IF(B27<=DATE(2026,3,31),159641000,IF(B27<=DATE(2026,12,31),545820000,IF(B27<=DATE(2027,6,30),797820000,IF(B27<=DATE(2028,3,31),1084000000,1084000000)))) -> 1084000000 | D27: =ГПР!AC16 -> 0 | E27: =ГПР!AC14 -> 0 | F27: =IF(A27<=Вводные!$B9,Структура_затрат!$H$35/Вводные!$B9,0) -> 0 | G27: =(E27+F27)*Вводные!$B18 -> 0 | H27: =MAX(0,E27+F27-G27) -> 0 | I27: =MIN(H27,MAX(0,C27-J27)) -> 0 | J27: =IF(A27=1,0,S26) -> 7.3997658e+08 | K27: =Продажи!L27 -> 1.4741871e+09 | L27: =IF((J27+I27)=0,0,K27/(J27+I27)) -> 1.9922078 | M27: =IF(L27>1.3,Вводные!$B26,IF(L27>1.2,Вводные!$B25,IF(L27>1.1,Вводные!$B24,IF(L27>=1,Вводные!$B23,Вводные!$B21+Вводные!$B22)))) -> 0.0001 | N27: =(J27+I27)*M27/12 -> 6166.4715 | O27: =IF(B27<=Вводные!$B27,N27,0) -> 0 | P27: =IF(B27<=Вводные!$B27,0,N27) -> 6166.4715 | Q27: =MAX(0,(C27-(J27+I27)))*Вводные!$B20/12 -> 83138.993 | R27: =IF(OR(YEAR(B27)>YEAR(Вводные!$B28),AND(YEAR(B27)=YEAR(Вводные!$B28),MONTH(B27)>=MONTH(Вводные!$B28))),MAX(0,MIN(J27+I27+O27+Q27,Продажи!N27-P27-Q27)),0) -> 0 | S27: =J27+I27+O27+Q27-R27 -> 7.4005972e+08 | T27: =IF(S27=0,"Кредит погашен",IF(L27<1,"Низкое покрытие","Рабочий режим")) -> Рабочий режим
A28: 25 | B28: 46784 | C28: =IF(B28<=DATE(2026,3,31),159641000,IF(B28<=DATE(2026,12,31),545820000,IF(B28<=DATE(2027,6,30),797820000,IF(B28<=DATE(2028,3,31),1084000000,1084000000)))) -> 1084000000 | D28: =ГПР!AD16 -> 0 | E28: =ГПР!AD14 -> 0 | F28: =IF(A28<=Вводные!$B9,Структура_затрат!$H$35/Вводные!$B9,0) -> 0 | G28: =(E28+F28)*Вводные!$B18 -> 0 | H28: =MAX(0,E28+F28-G28) -> 0 | I28: =MIN(H28,MAX(0,C28-J28)) -> 0 | J28: =IF(A28=1,0,S27) -> 7.4005972e+08 | K28: =Продажи!L28 -> 1.4741871e+09 | L28: =IF((J28+I28)=0,0,K28/(J28+I28)) -> 1.991984 | M28: =IF(L28>1.3,Вводные!$B26,IF(L28>1.2,Вводные!$B25,IF(L28>1.1,Вводные!$B24,IF(L28>=1,Вводные!$B23,Вводные!$B21+Вводные!$B22)))) -> 0.0001 | N28: =(J28+I28)*M28/12 -> 6167.1643 | O28: =IF(B28<=Вводные!$B27,N28,0) -> 0 | P28: =IF(B28<=Вводные!$B27,0,N28) -> 6167.1643 | Q28: =MAX(0,(C28-(J28+I28)))*Вводные!$B20/12 -> 83118.901 | R28: =IF(OR(YEAR(B28)>YEAR(Вводные!$B28),AND(YEAR(B28)=YEAR(Вводные!$B28),MONTH(B28)>=MONTH(Вводные!$B28))),MAX(0,MIN(J28+I28+O28+Q28,Продажи!N28-P28-Q28)),0) -> 0 | S28: =J28+I28+O28+Q28-R28 -> 7.4014284e+08 | T28: =IF(S28=0,"Кредит погашен",IF(L28<1,"Низкое покрытие","Рабочий режим")) -> Рабочий режим
A29: 26 | B29: 46813 | C29: =IF(B29<=DATE(2026,3,31),159641000,IF(B29<=DATE(2026,12,31),545820000,IF(B29<=DATE(2027,6,30),797820000,IF(B29<=DATE(2028,3,31),1084000000,1084000000)))) -> 1084000000 | D29: =ГПР!AE16 -> 0 | E29: =ГПР!AE14 -> 0 | F29: =IF(A29<=Вводные!$B9,Структура_затрат!$H$35/Вводные!$B9,0) -> 0 | G29: =(E29+F29)*Вводные!$B18 -> 0 | H29: =MAX(0,E29+F29-G29) -> 0 | I29: =MIN(H29,MAX(0,C29-J29)) -> 0 | J29: =IF(A29=1,0,S28) -> 7.4014284e+08 | K29: =Продажи!L29 -> 1.4741871e+09 | L29: =IF((J29+I29)=0,0,K29/(J29+I29)) -> 1.9917603 | M29: =IF(L29>1.3,Вводные!$B26,IF(L29>1.2,Вводные!$B25,IF(L29>1.1,Вводные!$B24,IF(L29>=1,Вводные!$B23,Вводные!$B21+Вводные!$B22)))) -> 0.0001 | N29: =(J29+I29)*M29/12 -> 6167.857 | O29: =IF(B29<=Вводные!$B27,N29,0) -> 0 | P29: =IF(B29<=Вводные!$B27,0,N29) -> 6167.857 | Q29: =MAX(0,(C29-(J29+I29)))*Вводные!$B20/12 -> 83098.814 | R29: =IF(OR(YEAR(B29)>YEAR(Вводные!$B28),AND(YEAR(B29)=YEAR(Вводные!$B28),MONTH(B29)>=MONTH(Вводные!$B28))),MAX(0,MIN(J29+I29+O29+Q29,Продажи!N29-P29-Q29)),0) -> 0 | S29: =J29+I29+O29+Q29-R29 -> 7.4022594e+08 | T29: =IF(S29=0,"Кредит погашен",IF(L29<1,"Низкое покрытие","Рабочий режим")) -> Рабочий режим
A30: 27 | B30: 46844 | C30: =IF(B30<=DATE(2026,3,31),159641000,IF(B30<=DATE(2026,12,31),545820000,IF(B30<=DATE(2027,6,30),797820000,IF(B30<=DATE(2028,3,31),1084000000,1084000000)))) -> 1084000000 | D30: =ГПР!AF16 -> 0 | E30: =ГПР!AF14 -> 0 | F30: =IF(A30<=Вводные!$B9,Структура_затрат!$H$35/Вводные!$B9,0) -> 0 | G30: =(E30+F30)*Вводные!$B18 -> 0 | H30: =MAX(0,E30+F30-G30) -> 0 | I30: =MIN(H30,MAX(0,C30-J30)) -> 0 | J30: =IF(A30=1,0,S29) -> 7.4022594e+08 | K30: =Продажи!L30 -> 1.4741871e+09 | L30: =IF((J30+I30)=0,0,K30/(J30+I30)) -> 1.9915367 | M30: =IF(L30>1.3,Вводные!$B26,IF(L30>1.2,Вводные!$B25,IF(L30>1.1,Вводные!$B24,IF(L30>=1,Вводные!$B23,Вводные!$B21+Вводные!$B22)))) -> 0.0001 | N30: =(J30+I30)*M30/12 -> 6168.5495 | O30: =IF(B30<=Вводные!$B27,N30,0) -> 0 | P30: =IF(B30<=Вводные!$B27,0,N30) -> 6168.5495 | Q30: =MAX(0,(C30-(J30+I30)))*Вводные!$B20/12 -> 83078.732 | R30: =IF(OR(YEAR(B30)>YEAR(Вводные!$B28),AND(YEAR(B30)=YEAR(Вводные!$B28),MONTH(B30)>=MONTH(Вводные!$B28))),MAX(0,MIN(J30+I30+O30+Q30,Продажи!N30-P30-Q30)),0) -> 0 | S30: =J30+I30+O30+Q30-R30 -> 7.4030901e+08 | T30: =IF(S30=0,"Кредит погашен",IF(L30<1,"Низкое покрытие","Рабочий режим")) -> Рабочий режим
A31: 28 | B31: 46874 | C31: =IF(B31<=DATE(2026,3,31),159641000,IF(B31<=DATE(2026,12,31),545820000,IF(B31<=DATE(2027,6,30),797820000,IF(B31<=DATE(2028,3,31),1084000000,1084000000)))) -> 1084000000 | D31: =ГПР!AG16 -> 0 | E31: =ГПР!AG14 -> 0 | F31: =IF(A31<=Вводные!$B9,Структура_затрат!$H$35/Вводные!$B9,0) -> 0 | G31: =(E31+F31)*Вводные!$B18 -> 0 | H31: =MAX(0,E31+F31-G31) -> 0 | I31: =MIN(H31,MAX(0,C31-J31)) -> 0 | J31: =IF(A31=1,0,S30) -> 7.4030901e+08 | K31: =Продажи!L31 -> 1.4741871e+09 | L31: =IF((J31+I31)=0,0,K31/(J31+I31)) -> 1.9913132 | M31: =IF(L31>1.3,Вводные!$B26,IF(L31>1.2,Вводные!$B25,IF(L31>1.1,Вводные!$B24,IF(L31>=1,Вводные!$B23,Вводные!$B21+Вводные!$B22)))) -> 0.0001 | N31: =(J31+I31)*M31/12 -> 6169.2418 | O31: =IF(B31<=Вводные!$B27,N31,0) -> 0 | P31: =IF(B31<=Вводные!$B27,0,N31) -> 6169.2418 | Q31: =MAX(0,(C31-(J31+I31)))*Вводные!$B20/12 -> 83058.655 | R31: =IF(OR(YEAR(B31)>YEAR(Вводные!$B28),AND(YEAR(B31)=YEAR(Вводные!$B28),MONTH(B31)>=MONTH(Вводные!$B28))),MAX(0,MIN(J31+I31+O31+Q31,Продажи!N31-P31-Q31)),0) -> 0 | S31: =J31+I31+O31+Q31-R31 -> 7.4039207e+08 | T31: =IF(S31=0,"Кредит погашен",IF(L31<1,"Низкое покрытие","Рабочий режим")) -> Рабочий режим
A32: 29 | B32: 46905 | C32: =IF(B32<=DATE(2026,3,31),159641000,IF(B32<=DATE(2026,12,31),545820000,IF(B32<=DATE(2027,6,30),797820000,IF(B32<=DATE(2028,3,31),1084000000,1084000000)))) -> 1084000000 | D32: =ГПР!AH16 -> 0 | E32: =ГПР!AH14 -> 0 | F32: =IF(A32<=Вводные!$B9,Структура_затрат!$H$35/Вводные!$B9,0) -> 0 | G32: =(E32+F32)*Вводные!$B18 -> 0 | H32: =MAX(0,E32+F32-G32) -> 0 | I32: =MIN(H32,MAX(0,C32-J32)) -> 0 | J32: =IF(A32=1,0,S31) -> 7.4039207e+08 | K32: =Продажи!L32 -> 1.4741871e+09 | L32: =IF((J32+I32)=0,0,K32/(J32+I32)) -> 1.9910898 | M32: =IF(L32>1.3,Вводные!$B26,IF(L32>1.2,Вводные!$B25,IF(L32>1.1,Вводные!$B24,IF(L32>=1,Вводные!$B23,Вводные!$B21+Вводные!$B22)))) -> 0.0001 | N32: =(J32+I32)*M32/12 -> 6169.9339 | O32: =IF(B32<=Вводные!$B27,N32,0) -> 0 | P32: =IF(B32<=Вводные!$B27,0,N32) -> 6169.9339 | Q32: =MAX(0,(C32-(J32+I32)))*Вводные!$B20/12 -> 83038.582 | R32: =IF(OR(YEAR(B32)>YEAR(Вводные!$B28),AND(YEAR(B32)=YEAR(Вводные!$B28),MONTH(B32)>=MONTH(Вводные!$B28))),MAX(0,MIN(J32+I32+O32+Q32,Продажи!N32-P32-Q32)),0) -> 0 | S32: =J32+I32+O32+Q32-R32 -> 7.4047511e+08 | T32: =IF(S32=0,"Кредит погашен",IF(L32<1,"Низкое покрытие","Рабочий режим")) -> Рабочий режим
A33: 30 | B33: 46935 | C33: =IF(B33<=DATE(2026,3,31),159641000,IF(B33<=DATE(2026,12,31),545820000,IF(B33<=DATE(2027,6,30),797820000,IF(B33<=DATE(2028,3,31),1084000000,1084000000)))) -> 1084000000 | D33: =ГПР!AI16 -> 0 | E33: =ГПР!AI14 -> 0 | F33: =IF(A33<=Вводные!$B9,Структура_затрат!$H$35/Вводные!$B9,0) -> 0 | G33: =(E33+F33)*Вводные!$B18 -> 0 | H33: =MAX(0,E33+F33-G33) -> 0 | I33: =MIN(H33,MAX(0,C33-J33)) -> 0 | J33: =IF(A33=1,0,S32) -> 7.4047511e+08 | K33: =Продажи!L33 -> 1.4741871e+09 | L33: =IF((J33+I33)=0,0,K33/(J33+I33)) -> 1.9908665 | M33: =IF(L33>1.3,Вводные!$B26,IF(L33>1.2,Вводные!$B25,IF(L33>1.1,Вводные!$B24,IF(L33>=1,Вводные!$B23,Вводные!$B21+Вводные!$B22)))) -> 0.0001 | N33: =(J33+I33)*M33/12 -> 6170.6259 | O33: =IF(B33<=Вводные!$B27,N33,0) -> 0 | P33: =IF(B33<=Вводные!$B27,0,N33) -> 6170.6259 | Q33: =MAX(0,(C33-(J33+I33)))*Вводные!$B20/12 -> 83018.515 | R33: =IF(OR(YEAR(B33)>YEAR(Вводные!$B28),AND(YEAR(B33)=YEAR(Вводные!$B28),MONTH(B33)>=MONTH(Вводные!$B28))),MAX(0,MIN(J33+I33+O33+Q33,Продажи!N33-P33-Q33)),0) -> 0 | S33: =J33+I33+O33+Q33-R33 -> 7.4055813e+08 | T33: =IF(S33=0,"Кредит погашен",IF(L33<1,"Низкое покрытие","Рабочий режим")) -> Рабочий режим
A34: 31 | B34: 46966 | C34: =IF(B34<=DATE(2026,3,31),159641000,IF(B34<=DATE(2026,12,31),545820000,IF(B34<=DATE(2027,6,30),797820000,IF(B34<=DATE(2028,3,31),1084000000,1084000000)))) -> 1084000000 | D34: =ГПР!AJ16 -> 0 | E34: =ГПР!AJ14 -> 0 | F34: =IF(A34<=Вводные!$B9,Структура_затрат!$H$35/Вводные!$B9,0) -> 0 | G34: =(E34+F34)*Вводные!$B18 -> 0 | H34: =MAX(0,E34+F34-G34) -> 0 | I34: =MIN(H34,MAX(0,C34-J34)) -> 0 | J34: =IF(A34=1,0,S33) -> 7.4055813e+08 | K34: =Продажи!L34 -> 1.4741871e+09 | L34: =IF((J34+I34)=0,0,K34/(J34+I34)) -> 1.9906433 | M34: =IF(L34>1.3,Вводные!$B26,IF(L34>1.2,Вводные!$B25,IF(L34>1.1,Вводные!$B24,IF(L34>=1,Вводные!$B23,Вводные!$B21+Вводные!$B22)))) -> 0.0001 | N34: =(J34+I34)*M34/12 -> 6171.3178 | O34: =IF(B34<=Вводные!$B27,N34,0) -> 0 | P34: =IF(B34<=Вводные!$B27,0,N34) -> 6171.3178 | Q34: =MAX(0,(C34-(J34+I34)))*Вводные!$B20/12 -> 82998.452 | R34: =IF(OR(YEAR(B34)>YEAR(Вводные!$B28),AND(YEAR(B34)=YEAR(Вводные!$B28),MONTH(B34)>=MONTH(Вводные!$B28))),MAX(0,MIN(J34+I34+O34+Q34,Продажи!N34-P34-Q34)),0) -> 0 | S34: =J34+I34+O34+Q34-R34 -> 7.4064113e+08 | T34: =IF(S34=0,"Кредит погашен",IF(L34<1,"Низкое покрытие","Рабочий режим")) -> Рабочий режим
A35: 32 | B35: 46997 | C35: =IF(B35<=DATE(2026,3,31),159641000,IF(B35<=DATE(2026,12,31),545820000,IF(B35<=DATE(2027,6,30),797820000,IF(B35<=DATE(2028,3,31),1084000000,1084000000)))) -> 1084000000 | D35: =ГПР!AK16 -> 0 | E35: =ГПР!AK14 -> 0 | F35: =IF(A35<=Вводные!$B9,Структура_затрат!$H$35/Вводные!$B9,0) -> 0 | G35: =(E35+F35)*Вводные!$B18 -> 0 | H35: =MAX(0,E35+F35-G35) -> 0 | I35: =MIN(H35,MAX(0,C35-J35)) -> 0 | J35: =IF(A35=1,0,S34) -> 7.4064113e+08 | K35: =Продажи!L35 -> 1.4741871e+09 | L35: =IF((J35+I35)=0,0,K35/(J35+I35)) -> 1.9904202 | M35: =IF(L35>1.3,Вводные!$B26,IF(L35>1.2,Вводные!$B25,IF(L35>1.1,Вводные!$B24,IF(L35>=1,Вводные!$B23,Вводные!$B21+Вводные!$B22)))) -> 0.0001 | N35: =(J35+I35)*M35/12 -> 6172.0094 | O35: =IF(B35<=Вводные!$B27,N35,0) -> 0 | P35: =IF(B35<=Вводные!$B27,0,N35) -> 6172.0094 | Q35: =MAX(0,(C35-(J35+I35)))*Вводные!$B20/12 -> 82978.394 | R35: =IF(OR(YEAR(B35)>YEAR(Вводные!$B28),AND(YEAR(B35)=YEAR(Вводные!$B28),MONTH(B35)>=MONTH(Вводные!$B28))),MAX(0,MIN(J35+I35+O35+Q35,Продажи!N35-P35-Q35)),0) -> 0 | S35: =J35+I35+O35+Q35-R35 -> 7.4072411e+08 | T35: =IF(S35=0,"Кредит погашен",IF(L35<1,"Низкое покрытие","Рабочий режим")) -> Рабочий режим
A36: 33 | B36: 47027 | C36: =IF(B36<=DATE(2026,3,31),159641000,IF(B36<=DATE(2026,12,31),545820000,IF(B36<=DATE(2027,6,30),797820000,IF(B36<=DATE(2028,3,31),1084000000,1084000000)))) -> 1084000000 | D36: =ГПР!AL16 -> 0 | E36: =ГПР!AL14 -> 0 | F36: =IF(A36<=Вводные!$B9,Структура_затрат!$H$35/Вводные!$B9,0) -> 0 | G36: =(E36+F36)*Вводные!$B18 -> 0 | H36: =MAX(0,E36+F36-G36) -> 0 | I36: =MIN(H36,MAX(0,C36-J36)) -> 0 | J36: =IF(A36=1,0,S35) -> 7.4072411e+08 | K36: =Продажи!L36 -> 1.4741871e+09 | L36: =IF((J36+I36)=0,0,K36/(J36+I36)) -> 1.9901973 | M36: =IF(L36>1.3,Вводные!$B26,IF(L36>1.2,Вводные!$B25,IF(L36>1.1,Вводные!$B24,IF(L36>=1,Вводные!$B23,Вводные!$B21+Вводные!$B22)))) -> 0.0001 | N36: =(J36+I36)*M36/12 -> 6172.7009 | O36: =IF(B36<=Вводные!$B27,N36,0) -> 0 | P36: =IF(B36<=Вводные!$B27,0,N36) -> 6172.7009 | Q36: =MAX(0,(C36-(J36+I36)))*Вводные!$B20/12 -> 82958.341 | R36: =IF(OR(YEAR(B36)>YEAR(Вводные!$B28),AND(YEAR(B36)=YEAR(Вводные!$B28),MONTH(B36)>=MONTH(Вводные!$B28))),MAX(0,MIN(J36+I36+O36+Q36,Продажи!N36-P36-Q36)),0) -> 0 | S36: =J36+I36+O36+Q36-R36 -> 7.4080707e+08 | T36: =IF(S36=0,"Кредит погашен",IF(L36<1,"Низкое покрытие","Рабочий режим")) -> Рабочий режим
A37: 34 | B37: 47058 | C37: =IF(B37<=DATE(2026,3,31),159641000,IF(B37<=DATE(2026,12,31),545820000,IF(B37<=DATE(2027,6,30),797820000,IF(B37<=DATE(2028,3,31),1084000000,1084000000)))) -> 1084000000 | D37: =ГПР!AM16 -> 0 | E37: =ГПР!AM14 -> 0 | F37: =IF(A37<=Вводные!$B9,Структура_затрат!$H$35/Вводные!$B9,0) -> 0 | G37: =(E37+F37)*Вводные!$B18 -> 0 | H37: =MAX(0,E37+F37-G37) -> 0 | I37: =MIN(H37,MAX(0,C37-J37)) -> 0 | J37: =IF(A37=1,0,S36) -> 7.4080707e+08 | K37: =Продажи!L37 -> 1.4741871e+09 | L37: =IF((J37+I37)=0,0,K37/(J37+I37)) -> 1.9899744 | M37: =IF(L37>1.3,Вводные!$B26,IF(L37>1.2,Вводные!$B25,IF(L37>1.1,Вводные!$B24,IF(L37>=1,Вводные!$B23,Вводные!$B21+Вводные!$B22)))) -> 0.0001 | N37: =(J37+I37)*M37/12 -> 6173.3922 | O37: =IF(B37<=Вводные!$B27,N37,0) -> 0 | P37: =IF(B37<=Вводные!$B27,0,N37) -> 6173.3922 | Q37: =MAX(0,(C37-(J37+I37)))*Вводные!$B20/12 -> 82938.292 | R37: =IF(OR(YEAR(B37)>YEAR(Вводные!$B28),AND(YEAR(B37)=YEAR(Вводные!$B28),MONTH(B37)>=MONTH(Вводные!$B28))),MAX(0,MIN(J37+I37+O37+Q37,Продажи!N37-P37-Q37)),0) -> 0 | S37: =J37+I37+O37+Q37-R37 -> 7.4089e+08 | T37: =IF(S37=0,"Кредит погашен",IF(L37<1,"Низкое покрытие","Рабочий режим")) -> Рабочий режим
A38: 35 | B38: 47088 | C38: =IF(B38<=DATE(2026,3,31),159641000,IF(B38<=DATE(2026,12,31),545820000,IF(B38<=DATE(2027,6,30),797820000,IF(B38<=DATE(2028,3,31),1084000000,1084000000)))) -> 1084000000 | D38: =ГПР!AN16 -> 0 | E38: =ГПР!AN14 -> 0 | F38: =IF(A38<=Вводные!$B9,Структура_затрат!$H$35/Вводные!$B9,0) -> 0 | G38: =(E38+F38)*Вводные!$B18 -> 0 | H38: =MAX(0,E38+F38-G38) -> 0 | I38: =MIN(H38,MAX(0,C38-J38)) -> 0 | J38: =IF(A38=1,0,S37) -> 7.4089e+08 | K38: =Продажи!L38 -> 1.4741871e+09 | L38: =IF((J38+I38)=0,0,K38/(J38+I38)) -> 1.9897516 | M38: =IF(L38>1.3,Вводные!$B26,IF(L38>1.2,Вводные!$B25,IF(L38>1.1,Вводные!$B24,IF(L38>=1,Вводные!$B23,Вводные!$B21+Вводные!$B22)))) -> 0.0001 | N38: =(J38+I38)*M38/12 -> 6174.0834 | O38: =IF(B38<=Вводные!$B27,N38,0) -> 0 | P38: =IF(B38<=Вводные!$B27,0,N38) -> 6174.0834 | Q38: =MAX(0,(C38-(J38+I38)))*Вводные!$B20/12 -> 82918.249 | R38: =IF(OR(YEAR(B38)>YEAR(Вводные!$B28),AND(YEAR(B38)=YEAR(Вводные!$B28),MONTH(B38)>=MONTH(Вводные!$B28))),MAX(0,MIN(J38+I38+O38+Q38,Продажи!N38-P38-Q38)),0) -> 0 | S38: =J38+I38+O38+Q38-R38 -> 7.4097292e+08 | T38: =IF(S38=0,"Кредит погашен",IF(L38<1,"Низкое покрытие","Рабочий режим")) -> Рабочий режим
A39: 36 | B39: 47119 | C39: =IF(B39<=DATE(2026,3,31),159641000,IF(B39<=DATE(2026,12,31),545820000,IF(B39<=DATE(2027,6,30),797820000,IF(B39<=DATE(2028,3,31),1084000000,1084000000)))) -> 1084000000 | D39: =ГПР!AO16 -> 0 | E39: =ГПР!AO14 -> 0 | F39: =IF(A39<=Вводные!$B9,Структура_затрат!$H$35/Вводные!$B9,0) -> 0 | G39: =(E39+F39)*Вводные!$B18 -> 0 | H39: =MAX(0,E39+F39-G39) -> 0 | I39: =MIN(H39,MAX(0,C39-J39)) -> 0 | J39: =IF(A39=1,0,S38) -> 7.4097292e+08 | K39: =Продажи!L39 -> 1.4741871e+09 | L39: =IF((J39+I39)=0,0,K39/(J39+I39)) -> 1.989529 | M39: =IF(L39>1.3,Вводные!$B26,IF(L39>1.2,Вводные!$B25,IF(L39>1.1,Вводные!$B24,IF(L39>=1,Вводные!$B23,Вводные!$B21+Вводные!$B22)))) -> 0.0001 | N39: =(J39+I39)*M39/12 -> 6174.7744 | O39: =IF(B39<=Вводные!$B27,N39,0) -> 0 | P39: =IF(B39<=Вводные!$B27,0,N39) -> 6174.7744 | Q39: =MAX(0,(C39-(J39+I39)))*Вводные!$B20/12 -> 82898.21 | R39: =IF(OR(YEAR(B39)>YEAR(Вводные!$B28),AND(YEAR(B39)=YEAR(Вводные!$B28),MONTH(B39)>=MONTH(Вводные!$B28))),MAX(0,MIN(J39+I39+O39+Q39,Продажи!N39-P39-Q39)),0) -> 0 | S39: =J39+I39+O39+Q39-R39 -> 7.4105582e+08 | T39: =IF(S39=0,"Кредит погашен",IF(L39<1,"Низкое покрытие","Рабочий режим")) -> Рабочий режим
A41: ИТОГО | N41: =SUM(N4:N39) -> 435985.63 | O41: =SUM(O4:O39) -> 324945.55 | P41: =SUM(P4:P39) -> 111040.08 | Q41: =SUM(Q4:Q39) -> 2586099.3 | S41: =MAX(S4:S39) -> 7.4105582e+08

Sheet Денежный_поток
A1: ДЕНЕЖНЫЙ ПОТОК ПРОЕКТА
A3: Месяц | B3: Дата | C3: CAPEX | D3: Коммерч. расходы | E3: Всего операционных затрат | F3: Собств. средства | G3: Выборка кредита | H3: Поступления на эскроу | I3: Доступно на обслуживание долга | J3: CFADS | K3: Проценты к оплате | L3: Комиссия | M3: Погашение долга | N3: Чистый поток после долга | O3: Накопленный поток
A4: 1 | B4: 46054 | C4: =Кредит!E4 -> 7074288 | D4: =Кредит!F4 -> 2764100.8 | E4: =C4+D4 -> 9838388.8 | F4: =Кредит!G4 -> 1478709.8 | G4: =Кредит!I4 -> 8359679 | H4: =Продажи!N4 -> 26453000 | I4: =Кредит!P4 -> 0 | J4: =Кредит!Q4 -> 36559.653 | K4: =Кредит!R4 -> 0 | L4: =F4+G4+H4-E4-I4-J4-K4 -> 26416440 | M4: =IF(A4=1,L4,M3+L4) -> 26416440 | N4: =F4+G4+I4-E4-K4-L4-M4 -> -52832881 | O4: =IF(A4=1,N4,O3+N4) -> -52832881
A5: 2 | B5: 46082 | C5: =Кредит!E5 -> 16790058 | D5: =Кредит!F5 -> 2764100.8 | E5: =C5+D5 -> 19554159 | F5: =Кредит!G5 -> 2938990.1 | G5: =Кредит!I5 -> 16615169 | H5: =Продажи!N5 -> 26623199 | I5: =Кредит!P5 -> 0 | J5: =Кредит!Q5 -> 32535.468 | K5: =Кредит!R5 -> 0 | L5: =F5+G5+H5-E5-I5-J5-K5 -> 26590664 | M5: =IF(A5=1,L5,M4+L5) -> 53007104 | N5: =F5+G5+I5-E5-K5-L5-M5 -> -79597768 | O5: =IF(A5=1,N5,O4+N5) -> -1.3243065e+08
A6: 3 | B6: 46113 | C6: =Кредит!E6 -> 37243785 | D6: =Кредит!F6 -> 2764100.8 | E6: =C6+D6 -> 40007886 | F6: =Кредит!G6 -> 6013185.2 | G6: =Кредит!I6 -> 33994701 | H6: =Продажи!N6 -> 26794494 | I6: =Кредит!P6 -> 0 | J6: =Кредит!Q6 -> 117638.76 | K6: =Кредит!R6 -> 0 | L6: =F6+G6+H6-E6-I6-J6-K6 -> 26676855 | M6: =IF(A6=1,L6,M5+L6) -> 79683959 | N6: =F6+G6+I6-E6-K6-L6-M6 -> -1.0636081e+08 | O6: =IF(A6=1,N6,O5+N6) -> -2.3879146e+08
A7: 4 | B7: 46143 | C7: =Кредит!E7 -> 27528015 | D7: =Кредит!F7 -> 2764100.8 | E7: =C7+D7 -> 30292116 | F7: =Кредит!G7 -> 4552905 | G7: =Кредит!I7 -> 25739211 | H7: =Продажи!N7 -> 26966890 | I7: =Кредит!P7 -> 0 | J7: =Кредит!Q7 -> 111389.9 | K7: =Кредит!R7 -> 0 | L7: =F7+G7+H7-E7-I7-J7-K7 -> 26855501 | M7: =IF(A7=1,L7,M6+L7) -> 1.0653946e+08 | N7: =F7+G7+I7-E7-K7-L7-M7 -> -1.3339496e+08 | O7: =IF(A7=1,N7,O6+N7) -> -3.7218642e+08
A8: 5 | B8: 46174 | C8: =Кредит!E8 -> 51397623 | D8: =Кредит!F8 -> 2764100.8 | E8: =C8+D8 -> 54161724 | F8: =Кредит!G8 -> 8140507.1 | G8: =Кредит!I8 -> 46021217 | H8: =Продажи!N8 -> 54280792 | I8: =Кредит!P8 -> 0 | J8: =Кредит!Q8 -> 100215.37 | K8: =Кредит!R8 -> 0 | L8: =F8+G8+H8-E8-I8-J8-K8 -> 54180577 | M8: =IF(A8=1,L8,M7+L8) -> 1.6072004e+08 | N8: =F8+G8+I8-E8-K8-L8-M8 -> -2.1490061e+08 | O8: =IF(A8=1,N8,O7+N8) -> -5.8708704e+08
A9: 6 | B9: 46204 | C9: =Кредит!E9 -> 23869608 | D9: =Кредит!F9 -> 2764100.8 | E9: =C9+D9 -> 26633709 | F9: =Кредит!G9 -> 4003046.4 | G9: =Кредит!I9 -> 22630662 | H9: =Продажи!N9 -> 54630037 | I9: =Кредит!P9 -> 0 | J9: =Кредит!Q9 -> 94682.2 | K9: =Кредит!R9 -> 0 | L9: =F9+G9+H9-E9-I9-J9-K9 -> 54535355 | M9: =IF(A9=1,L9,M8+L9) -> 2.1525539e+08 | N9: =F9+G9+I9-E9-K9-L9-M9 -> -2.6979075e+08 | O9: =IF(A9=1,N9,O8+N9) -> -8.5687778e+08
A10: 7 | B10: 46235 | C10: =Кредит!E10 -> 23869608 | D10: =Кредит!F10 -> 2764100.8 | E10: =C10+D10 -> 26633709 | F10: =Кредит!G10 -> 4003046.4 | G10: =Кредит!I10 -> 22630662 | H10: =Продажи!N10 -> 82472292 | I10: =Кредит!P10 -> 0 | J10: =Кредит!Q10 -> 89189.931 | K10: =Кредит!R10 -> 0 | L10: =F10+G10+H10-E10-I10-J10-K10 -> 82383102 | M10: =IF(A10=1,L10,M9+L10) -> 2.9763849e+08 | N10: =F10+G10+I10-E10-K10-L10-M10 -> -3.800216e+08 | O10: =IF(A10=1,N10,O9+N10) -> -1.2368994e+09
A11: 8 | B11: 46266 | C11: =Кредит!E11 -> 23869608 | D11: =Кредит!F11 -> 2764100.8 | E11: =C11+D11 -> 26633709 | F11: =Кредит!G11 -> 4003046.4 | G11: =Кредит!I11 -> 22630662 | H11: =Продажи!N11 -> 83002921 | I11: =Кредит!P11 -> 0 | J11: =Кредит!Q11 -> 83698.944 | K11: =Кредит!R11 -> 0 | L11: =F11+G11+H11-E11-I11-J11-K11 -> 82919222 | M11: =IF(A11=1,L11,M10+L11) -> 3.8055772e+08 | N11: =F11+G11+I11-E11-K11-L11-M11 -> -4.6347694e+08 | O11: =IF(A11=1,N11,O10+N11) -> -1.7003763e+09
A12: 9 | B12: 46296 | C12: =Кредит!E12 -> 81285182 | D12: =Кредит!F12 -> 2764100.8 | E12: =C12+D12 -> 84049283 | F12: =Кредит!G12 -> 12632607 | G12: =Кредит!I12 -> 71416676 | H12: =Продажи!N12 -> 1.1138262e+08 | I12: =Кредит!P12 -> 0 | J12: =Кредит!Q12 -> 66419.286 | K12: =Кредит!R12 -> 0 | L12: =F12+G12+H12-E12-I12-J12-K12 -> 1.113162e+08 | M12: =IF(A12=1,L12,M11+L12) -> 4.9187392e+08 | N12: =F12+G12+I12-E12-K12-L12-M12 -> -6.0319012e+08 | O12: =IF(A12=1,N12,O11+N12) -> -2.3035664e+09
A13: 10 | B13: 46327 | C13: =Кредит!E13 -> 85988273 | D13: =Кредит!F13 -> 2764100.8 | E13: =C13+D13 -> 88752374 | F13: =Кредит!G13 -> 13339482 | G13: =Кредит!I13 -> 75412892 | H13: =Продажи!N13 -> 1.1209926e+08 | I13: =Кредит!P13 -> 0 | J13: =Кредит!Q13 -> 48177.906 | K13: =Кредит!R13 -> 0 | L13: =F13+G13+H13-E13-I13-J13-K13 -> 1.1205108e+08 | M13: =IF(A13=1,L13,M12+L13) -> 6.03925e+08 | N13: =F13+G13+I13-E13-K13-L13-M13 -> -7.1597608e+08 | O13: =IF(A13=1,N13,O12+N13) -> -3.0195425e+09
A14: 11 | B14: 46357 | C14: =Кредит!E14 -> 96873534 | D14: =Кредит!F14 -> 2764100.8 | E14: =C14+D14 -> 99637635 | F14: =Кредит!G14 -> 14975537 | G14: =Кредит!I14 -> 84662098 | H14: =Продажи!N14 -> 1.4262564e+08 | I14: =Кредит!P14 -> 0 | J14: =Кредит!Q14 -> 27705.558 | K14: =Кредит!R14 -> 0 | L14: =F14+G14+H14-E14-I14-J14-K14 -> 1.4259793e+08 | M14: =IF(A14=1,L14,M13+L14) -> 7.4652293e+08 | N14: =F14+G14+I14-E14-K14-L14-M14 -> -8.8912086e+08 | O14: =IF(A14=1,N14,O13+N14) -> -3.9086634e+09
A15: 12 | B15: 46388 | C15: =Кредит!E15 -> 96873534 | D15: =Кредит!F15 -> 2764100.8 | E15: =C15+D15 -> 99637635 | F15: =Кредит!G15 -> 14975537 | G15: =Кредит!I15 -> 84662098 | H15: =Продажи!N15 -> 1.43533e+08 | I15: =Кредит!P15 -> 0 | J15: =Кредит!Q15 -> 68137.987 | K15: =Кредит!R15 -> 0 | L15: =F15+G15+H15-E15-I15-J15-K15 -> 1.4346486e+08 | M15: =IF(A15=1,L15,M14+L15) -> 8.8998779e+08 | N15: =F15+G15+I15-E15-K15-L15-M15 -> -1.0334526e+09 | O15: =IF(A15=1,N15,O14+N15) -> -4.942116e+09
... A39: 36 | B39: 47119 | C39: =Кредит!E39 -> 0 | D39: =Кредит!F39 -> 0 | E39: =C39+D39 -> 0 | F39: =Кредит!G39 -> 0 | G39: =Кредит!I39 -> 0 | H39: =Продажи!N39 -> 0 | I39: =Кредит!P39 -> 6174.7744 | J39: =Кредит!Q39 -> 82898.21 | K39: =Кредит!R39 -> 0 | L39: =F39+G39+H39-E39-I39-J39-K39 -> -89072.985 | M39: =IF(A39=1,L39,M38+L39) -> 1.47149e+09 | N39: =F39+G39+I39-E39-K39-L39-M39 -> -1.4713947e+09 | O39: =IF(A39=1,N39,O38+N39) -> -3.9983534e+10
A41: ИТОГО | C41: =SUM(C4:C39) -> 8.2448661e+08 | D41: =SUM(D4:D39) -> 44225613 | E41: =SUM(E4:E39) -> 8.6871222e+08 | F41: =SUM(F4:F39) -> 1.3056745e+08 | G41: =SUM(G4:G39) -> 7.3814478e+08 | H41: =SUM(H4:H39) -> 1.4741871e+09 | I41: =SUM(I4:I39) -> 111040.08 | J41: =SUM(J4:J39) -> 2586099.3 | ... M41: =SUM(M4:M39) -> 3.8512155e+10

Sheet Поставки
A1: ГРАФИК ПОСТАВОК МАТЕРИАЛОВ
A3: Месяц | B3: Дата потребности | C3: Бетон, м3 | D3: Арматура, т | E3: Фасадные материалы, руб | F3: Инженерное оборудование, руб | G3: Дата заказа бетона | H3: Дата заказа арматуры | I3: Дата заказа фасада | J3: Комментарий
A4: 1 | B4: 46054 | C4: =IF(AND(A4>=3,A4<=18),Вводные!$B10*Вводные!$B69/16,0) -> 0 | D4: =IF(AND(A4>=3,A4<=18),Вводные!$B10*Вводные!$B70/16,0) -> 0 | E4: =IF(AND(A4>=12,A4<=20),Структура_затрат!H14/9,0) -> 0 | F4: =IF(AND(A4>=13,A4<=22),SUM(Структура_затрат!H18:H22)/10,0) -> 0 | G4: 46023 | H4: 45992 | I4: 45992 | J4: Проверить срок логистики по региону
A5: 2 | B5: 46082 | C5: =IF(AND(A5>=3,A5<=18),Вводные!$B10*Вводные!$B69/16,0) -> 0 | D5: =IF(AND(A5>=3,A5<=18),Вводные!$B10*Вводные!$B70/16,0) -> 0 | E5: =IF(AND(A5>=12,A5<=20),Структура_затрат!H14/9,0) -> 0 | F5: =IF(AND(A5>=13,A5<=22),SUM(Структура_затрат!H18:H22)/10,0) -> 0 | G5: 46054 | H5: 46023 | I5: 46023 | J5: Проверить срок логистики по региону
A6: 3 | B6: 46113 | C6: =IF(AND(A6>=3,A6<=18),Вводные!$B10*Вводные!$B69/16,0) -> 0 | D6: =IF(AND(A6>=3,A6<=18),Вводные!$B10*Вводные!$B70/16,0) -> 0 | E6: =IF(AND(A6>=12,A6<=20),Структура_затрат!H14/9,0) -> 0 | F6: =IF(AND(A6>=13,A6<=22),SUM(Структура_затрат!H18:H22)/10,0) -> 0 | G6: 46082 | H6: 46054 | I6: 46054 | J6: Проверить срок логистики по региону
A7: 4 | B7: 46143 | C7: =IF(AND(A7>=3,A7<=18),Вводные!$B10*Вводные!$B69/16,0) -> 0 | D7: =IF(AND(A7>=3,A7<=18),Вводные!$B10*Вводные!$B70/16,0) -> 0 | E7: =IF(AND(A7>=12,A7<=20),Структура_затрат!H14/9,0) -> 0 | F7: =IF(AND(A7>=13,A7<=22),SUM(Структура_затрат!H18:H22)/10,0) -> 0 | G7: 46113 | H7: 46082 | I7: 46082 | J7: Проверить срок логистики по региону
A8: 5 | B8: 46174 | C8: =IF(AND(A8>=3,A8<=18),Вводные!$B10*Вводные!$B69/16,0) -> 0 | D8: =IF(AND(A8>=3,A8<=18),Вводные!$B10*Вводные!$B70/16,0) -> 0 | E8: =IF(AND(A8>=12,A8<=20),Структура_затрат!H14/9,0) -> 0 | F8: =IF(AND(A8>=13,A8<=22),SUM(Структура_затрат!H18:H22)/10,0) -> 0 | G8: 46143 | H8: 46113 | I8: 46113 | J8: Проверить срок логистики по региону
A9: 6 | B9: 46204 | C9: =IF(AND(A9>=3,A9<=18),Вводные!$B10*Вводные!$B69/16,0) -> 0 | D9: =IF(AND(A9>=3,A9<=18),Вводные!$B10*Вводные!$B70/16,0) -> 0 | E9: =IF(AND(A9>=12,A9<=20),Структура_затрат!H14/9,0) -> 0 | F9: =IF(AND(A9>=13,A9<=22),SUM(Структура_затрат!H18:H22)/10,0) -> 0 | G9: 46174 | H9: 46143 | I9: 46143 | J9: Проверить срок логистики по региону
A10: 7 | B10: 46235 | C10: =IF(AND(A10>=3,A10<=18),Вводные!$B10*Вводные!$B69/16,0) -> 0 | D10: =IF(AND(A10>=3,A10<=18),Вводные!$B10*Вводные!$B70/16,0) -> 0 | E10: =IF(AND(A10>=12,A10<=20),Структура_затрат!H14/9,0) -> 0 | F10: =IF(AND(A10>=13,A10<=22),SUM(Структура_затрат!H18:H22)/10,0) -> 0 | G10: 46204 | H10: 46174 | I10: 46174 | J10: Проверить срок логистики по региону
A11: 8 | B11: 46266 | C11: =IF(AND(A11>=3,A11<=18),Вводные!$B10*Вводные!$B69/16,0) -> 0 | D11: =IF(AND(A11>=3,A11<=18),Вводные!$B10*Вводные!$B70/16,0) -> 0 | E11: =IF(AND(A11>=12,A11<=20),Структура_затрат!H14/9,0) -> 0 | F11: =IF(AND(A11>=13,A11<=22),SUM(Структура_затрат!H18:H22)/10,0) -> 0 | G11: 46235 | H11: 46204 | I11: 46204 | J11: Проверить срок логистики по региону
A12: 9 | B12: 46296 | C12: =IF(AND(A12>=3,A12<=18),Вводные!$B10*Вводные!$B69/16,0) -> 0 | D12: =IF(AND(A12>=3,A12<=18),Вводные!$B10*Вводные!$B70/16,0) -> 0 | E12: =IF(AND(A12>=12,A12<=20),Структура_затрат!H14/9,0) -> 0 | F12: =IF(AND(A12>=13,A12<=22),SUM(Структура_затрат!H18:H22)/10,0) -> 0 | G12: 46266 | H12: 46235 | I12: 46235 | J12: Проверить срок логистики по региону
A13: 10 | B13: 46327 | C13: =IF(AND(A13>=3,A13<=18),Вводные!$B10*Вводные!$B69/16,0) -> 0 | D13: =IF(AND(A13>=3,A13<=18),Вводные!$B10*Вводные!$B70/16,0) -> 0 | E13: =IF(AND(A13>=12,A13<=20),Структура_затрат!H14/9,0) -> 0 | F13: =IF(AND(A13>=13,A13<=22),SUM(Структура_затрат!H18:H22)/10,0) -> 0 | G13: 46296 | H13: 46266 | I13: 46266 | J13: Проверить срок логистики по региону
A14: 11 | B14: 46357 | C14: =IF(AND(A14>=3,A14<=18),Вводные!$B10*Вводные!$B69/16,0) -> 0 | D14: =IF(AND(A14>=3,A14<=18),Вводные!$B10*Вводные!$B70/16,0) -> 0 | E14: =IF(AND(A14>=12,A14<=20),Структура_затрат!H14/9,0) -> 0 | F14: =IF(AND(A14>=13,A14<=22),SUM(Структура_затрат!H18:H22)/10,0) -> 0 | G14: 46327 | H14: 46296 | I14: 46296 | J14: Проверить срок логистики по региону
A15: 12 | B15: 46388 | C15: =IF(AND(A15>=3,A15<=18),Вводные!$B10*Вводные!$B69/16,0) -> 0 | D15: =IF(AND(A15>=3,A15<=18),Вводные!$B10*Вводные!$B70/16,0) -> 0 | E15: =IF(AND(A15>=12,A15<=20),Структура_затрат!H14/9,0) -> 11634934 | F15: =IF(AND(A15>=13,A15<=22),SUM(Структура_затрат!H18:H22)/10,0) -> 0 | G15: 46357 | H15: 46327 | I15: 46327 | J15: Проверить срок логистики по региону
A16: 13 | B16: 46419 | C16: =IF(AND(A16>=3,A16<=18),Вводные!$B10*Вводные!$B69/16,0) -> 0 | D16: =IF(AND(A16>=3,A16<=18),Вводные!$B10*Вводные!$B70/16,0) -> 0 | E16: =IF(AND(A16>=12,A16<=20),Структура_затрат!H14/9,0) -> 11634934 | F16: =IF(AND(A16>=13,A16<=22),SUM(Структура_затрат!H18:H22)/10,0) -> 17142936 | G16: 46388 | H16: 46357 | I16: 46357 | J16: Проверить срок логистики по региону
A17: 14 | B17: 46447 | C17: =IF(AND(A17>=3,A17<=18),Вводные!$B10*Вводные!$B69/16,0) -> 0 | D17: =IF(AND(A17>=3,A17<=18),Вводные!$B10*Вводные!$B70/16,0) -> 0 | E17: =IF(AND(A17>=12,A17<=20),Структура_затрат!H14/9,0) -> 11634934 | F17: =IF(AND(A17>=13,A17<=22),SUM(Структура_затрат!H18:H22)/10,0) -> 17142936 | G17: 46419 | H17: 46388 | I17: 46388 | J17: Проверить срок логистики по региону
A18: 15 | B18: 46478 | C18: =IF(AND(A18>=3,A18<=18),Вводные!$B10*Вводные!$B69/16,0) -> 0 | D18: =IF(AND(A18>=3,A18<=18),Вводные!$B10*Вводные!$B70/16,0) -> 0 | E18: =IF(AND(A18>=12,A18<=20),Структура_затрат!H14/9,0) -> 11634934 | F18: =IF(AND(A18>=13,A18<=22),SUM(Структура_затрат!H18:H22)/10,0) -> 17142936 | G18: 46447 | H18: 46419 | I18: 46419 | J18: Проверить срок логистики по региону
A19: 16 | B19: 46508 | C19: =IF(AND(A19>=3,A19<=18),Вводные!$B10*Вводные!$B69/16,0) -> 0 | D19: =IF(AND(A19>=3,A19<=18),Вводные!$B10*Вводные!$B70/16,0) -> 0 | E19: =IF(AND(A19>=12,A19<=20),Структура_затрат!H14/9,0) -> 11634934 | F19: =IF(AND(A19>=13,A19<=22),SUM(Структура_затрат!H18:H22)/10,0) -> 17142936 | G19: 46478 | H19: 46447 | I19: 46447 | J19: Проверить срок логистики по региону
A20: 17 | B20: 46539 | C20: =IF(AND(A20>=3,A20<=18),Вводные!$B10*Вводные!$B69/16,0) -> 0 | D20: =IF(AND(A20>=3,A20<=18),Вводные!$B10*Вводные!$B70/16,0) -> 0 | E20: =IF(AND(A20>=12,A20<=20),Структура_затрат!H14/9,0) -> 11634934 | F20: =IF(AND(A20>=13,A20<=22),SUM(Структура_затрат!H18:H22)/10,0) -> 17142936 | G20: 46508 | H20: 46478 | I20: 46478 | J20: Проверить срок логистики по региону
A21: 18 | B21: 46569 | C21: =IF(AND(A21>=3,A21<=18),Вводные!$B10*Вводные!$B69/16,0) -> 0 | D21: =IF(AND(A21>=3,A21<=18),Вводные!$B10*Вводные!$B70/16,0) -> 0 | E21: =IF(AND(A21>=12,A21<=20),Структура_затрат!H14/9,0) -> 11634934 | F21: =IF(AND(A21>=13,A21<=22),SUM(Структура_затрат!H18:H22)/10,0) -> 17142936 | G21: 46539 | H21: 46508 | I21: 46508 | J21: Проверить срок логистики по региону
A22: 19 | B22: 46600 | C22: =IF(AND(A22>=3,A22<=18),Вводные!$B10*Вводные!$B69/16,0) -> 0 | D22: =IF(AND(A22>=3,A22<=18),Вводные!$B10*Вводные!$B70/16,0) -> 0 | E22: =IF(AND(A22>=12,A22<=20),Структура_затрат!H14/9,0) -> 11634934 | F22: =IF(AND(A22>=13,A22<=22),SUM(Структура_затрат!H18:H22)/10,0) -> 17142936 | G22: 46569 | H22: 46539 | I22: 46539 | J22: Проверить срок логистики по региону
A23: 20 | B23: 46631 | C23: =IF(AND(A23>=3,A23<=18),Вводные!$B10*Вводные!$B69/16,0) -> 0 | D23: =IF(AND(A23>=3,A23<=18),Вводные!$B10*Вводные!$B70/16,0) -> 0 | E23: =IF(AND(A23>=12,A23<=20),Структура_затрат!H14/9,0) -> 11634934 | F23: =IF(AND(A23>=13,A23<=22),SUM(Структура_затрат!H18:H22)/10,0) -> 17142936 | G23: 46600 | H23: 46569 | I23: 46569 | J23: Проверить срок логистики по региону
A24: 21 | B24: 46661 | C24: =IF(AND(A24>=3,A24<=18),Вводные!$B10*Вводные!$B69/16,0) -> 0 | D24: =IF(AND(A24>=3,A24<=18),Вводные!$B10*Вводные!$B70/16,0) -> 0 | E24: =IF(AND(A24>=12,A24<=20),Структура_затрат!H14/9,0) -> 0 | F24: =IF(AND(A24>=13,A24<=22),SUM(Структура_затрат!H18:H22)/10,0) -> 17142936 | G24: 46631 | H24: 46600 | I24: 46600 | J24: Проверить срок логистики по региону
A25: 22 | B25: 46692 | C25: =IF(AND(A25>=3,A25<=18),Вводные!$B10*Вводные!$B69/16,0) -> 0 | D25: =IF(AND(A25>=3,A25<=18),Вводные!$B10*Вводные!$B70/16,0) -> 0 | E25: =IF(AND(A25>=12,A25<=20),Структура_затрат!H14/9,0) -> 0 | F25: =IF(AND(A25>=13,A25<=22),SUM(Структура_затрат!H18:H22)/10,0) -> 17142936 | G25: 46661 | H25: 46631 | I25: 46631 | J25: Проверить срок логистики по региону
A26: 23 | B26: 46722 | C26: =IF(AND(A26>=3,A26<=18),Вводные!$B10*Вводные!$B69/16,0) -> 0 | D26: =IF(AND(A26>=3,A26<=18),Вводные!$B10*Вводные!$B70/16,0) -> 0 | E26: =IF(AND(A26>=12,A26<=20),Структура_затрат!H14/9,0) -> 0 | F26: =IF(AND(A26>=13,A26<=22),SUM(Структура_затрат!H18:H22)/10,0) -> 0 | G26: 46692 | H26: 46661 | I26: 46661 | J26: Проверить срок логистики по региону
A27: 24 | B27: 46753 | C27: =IF(AND(A27>=3,A27<=18),Вводные!$B10*Вводные!$B69/16,0) -> 0 | D27: =IF(AND(A27>=3,A27<=18),Вводные!$B10*Вводные!$B70/16,0) -> 0 | E27: =IF(AND(A27>=12,A27<=20),Структура_затрат!H14/9,0) -> 0 | F27: =IF(AND(A27>=13,A27<=22),SUM(Структура_затрат!H18:H22)/10,0) -> 0 | G27: 46722 | H27: 46692 | I27: 46692 | J27: Проверить срок логистики по региону
A28: 25 | B28: 46784 | C28: =IF(AND(A28>=3,A28<=18),Вводные!$B10*Вводные!$B69/16,0) -> 0 | D28: =IF(AND(A28>=3,A28<=18),Вводные!$B10*Вводные!$B70/16,0) -> 0 | E28: =IF(AND(A28>=12,A28<=20),Структура_затрат!H14/9,0) -> 0 | F28: =IF(AND(A28>=13,A28<=22),SUM(Структура_затрат!H18:H22)/10,0) -> 0 | G28: 46753 | H28: 46722 | I28: 46722 | J28: Проверить срок логистики по региону
A29: 26 | B29: 46813 | C29: =IF(AND(A29>=3,A29<=18),Вводные!$B10*Вводные!$B69/16,0) -> 0 | D29: =IF(AND(A29>=3,A29<=18),Вводные!$B10*Вводные!$B70/16,0) -> 0 | E29: =IF(AND(A29>=12,A29<=20),Структура_затрат!H14/9,0) -> 0 | F29: =IF(AND(A29>=13,A29<=22),SUM(Структура_затрат!H18:H22)/10,0) -> 0 | G29: 46784 | H29: 46753 | I29: 46753 | J29: Проверить срок логистики по региону
A30: 27 | B30: 46844 | C30: =IF(AND(A30>=3,A30<=18),Вводные!$B10*Вводные!$B69/16,0) -> 0 | D30: =IF(AND(A30>=3,A30<=18),Вводные!$B10*Вводные!$B70/16,0) -> 0 | E30: =IF(AND(A30>=12,A30<=20),Структура_затрат!H14/9,0) -> 0 | F30: =IF(AND(A30>=13,A30<=22),SUM(Структура_затрат!H18:H22)/10,0) -> 0 | G30: 46813 | H30: 46784 | I30: 46784 | J30: Проверить срок логистики по региону
A31: 28 | B31: 46874 | C31: =IF(AND(A31>=3,A31<=18),Вводные!$B10*Вводные!$B69/16,0) -> 0 | D31: =IF(AND(A31>=3,A31<=18),Вводные!$B10*Вводные!$B70/16,0) -> 0 | E31: =IF(AND(A31>=12,A31<=20),Структура_затрат!H14/9,0) -> 0 | F31: =IF(AND(A31>=13,A31<=22),SUM(Структура_затрат!H18:H22)/10,0) -> 0 | G31: 46844 | H31: 46813 | I31: 46813 | J31: Проверить срок логистики по региону
A32: 29 | B32: 46905 | C32: =IF(AND(A32>=3,A32<=18),Вводные!$B10*Вводные!$B69/16,0) -> 0 | D32: =IF(AND(A32>=3,A32<=18),Вводные!$B10*Вводные!$B70/16,0) -> 0 | E32: =IF(AND(A32>=12,A32<=20),Структура_затрат!H14/9,0) -> 0 | F32: =IF(AND(A32>=13,A32<=22),SUM(Структура_затрат!H18:H22)/10,0) -> 0 | G32: 46874 | H32: 46844 | I32: 46844 | J32: Проверить срок логистики по региону
A33: 30 | B33: 46935 | C33: =IF(AND(A33>=3,A33<=18),Вводные!$B10*Вводные!$B69/16,0) -> 0 | D33: =IF(AND(A33>=3,A33<=18),Вводные!$B10*Вводные!$B70/16,0) -> 0 | E33: =IF(AND(A33>=12,A33<=20),Структура_затрат!H14/9,0) -> 0 | F33: =IF(AND(A33>=13,A33<=22),SUM(Структура_затрат!H18:H22)/10,0) -> 0 | G33: 46905 | H33: 46874 | I33: 46874 | J33: Проверить срок логистики по региону
A34: 31 | B34: 46966 | C34: =IF(AND(A34>=3,A34<=18),Вводные!$B10*Вводные!$B69/16,0) -> 0 | D34: =IF(AND(A34>=3,A34<=18),Вводные!$B10*Вводные!$B70/16,0) -> 0 | E34: =IF(AND(A34>=12,A34<=20),Структура_затрат!H14/9,0) -> 0 | F34: =IF(AND(A34>=13,A34<=22),SUM(Структура_затрат!H18:H22)/10,0) -> 0 | G34: 46935 | H34: 46905 | I34: 46905 | J34: Проверить срок логистики по региону
A35: 32 | B35: 46997 | C35: =IF(AND(A35>=3,A35<=18),Вводные!$B10*Вводные!$B69/16,0) -> 0 | D35: =IF(AND(A35>=3,A35<=18),Вводные!$B10*Вводные!$B70/16,0) -> 0 | E35: =IF(AND(A35>=12,A35<=20),Структура_затрат!H14/9,0) -> 0 | F35: =IF(AND(A35>=13,A35<=22),SUM(Структура_затрат!H18:H22)/10,0) -> 0 | G35: 46966 | H35: 46935 | I35: 46935 | J35: Проверить срок логистики по региону
A36: 33 | B36: 47027 | C36: =IF(AND(A36>=3,A36<=18),Вводные!$B10*Вводные!$B69/16,0) -> 0 | D36: =IF(AND(A36>=3,A36<=18),Вводные!$B10*Вводные!$B70/16,0) -> 0 | E36: =IF(AND(A36>=12,A36<=20),Структура_затрат!H14/9,0) -> 0 | F36: =IF(AND(A36>=13,A36<=22),SUM(Структура_затрат!H18:H22)/10,0) -> 0 | G36: 46997 | H36: 46966 | I36: 46966 | J36: Проверить срок логистики по региону
A37: 34 | B37: 47058 | C37: =IF(AND(A37>=3,A37<=18),Вводные!$B10*Вводные!$B69/16,0) -> 0 | D37: =IF(AND(A37>=3,A37<=18),Вводные!$B10*Вводные!$B70/16,0) -> 0 | E37: =IF(AND(A37>=12,A37<=20),Структура_затрат!H14/9,0) -> 0 | F37: =IF(AND(A37>=13,A37<=22),SUM(Структура_затрат!H18:H22)/10,0) -> 0 | G37: 47027 | H37: 46997 | I37: 46997 | J37: Проверить срок логистики по региону
A38: 35 | B38: 47088 | C38: =IF(AND(A38>=3,A38<=18),Вводные!$B10*Вводные!$B69/16,0) -> 0 | D38: =IF(AND(A38>=3,A38<=18),Вводные!$B10*Вводные!$B70/16,0) -> 0 | E38: =IF(AND(A38>=12,A38<=20),Структура_затрат!H14/9,0) -> 0 | F38: =IF(AND(A38>=13,A38<=22),SUM(Структура_затрат!H18:H22)/10,0) -> 0 | G38: 47058 | H38: 47027 | I38: 47027 | J38: Проверить срок логистики по региону
A39: 36 | B39: 47119 | C39: =IF(AND(A39>=3,A39<=18),Вводные!$B10*Вводные!$B69/16,0) -> 0 | D39: =IF(AND(A39>=3,A39<=18),Вводные!$B10*Вводные!$B70/16,0) -> 0 | E39: =IF(AND(A39>=12,A39<=20),Структура_затрат!H14/9,0) -> 0 | F39: =IF(AND(A39>=13,A39<=22),SUM(Структура_затрат!H18:H22)/10,0) -> 0 | G39: 47088 | H39: 47058 | I39: 47058 | J39: Проверить срок логистики по региону

Sheet ДСCR
A1: DSCR / КВАРТАЛЬНЫЙ КОНТРОЛЬ
A3: Квартал | B3: Период | C3: Поступления на обслуживание долга | D3: Операционные расходы | E3: CFADS | F3: Debt Service | G3: Целевой DSCR | H3: DSCR | I3: Статус
A4: Q1 | B4: М1-М3 | C4: =SUM(Денежный_поток!H4:H6) -> 79870693 | D4: =SUM(Денежный_поток!E4:E6) -> 69400433 | E4: =SUM(Денежный_поток!I4:K6) -> 186733.88 | F4: =E4 -> 186733.88 | G4: =MAX(0,C4-D4) -> 10470260 | H4: =IF(F4=0,"",G4/F4) -> 56.070488 | I4: =IF(H4="","",IF(H4>=Вводные!$B29,"OK","RISK")) -> OK
A5: Q2 | B5: М4-М6 | C5: =SUM(Денежный_поток!H7:H9) -> 1.3587772e+08 | D5: =SUM(Денежный_поток!E7:E9) -> 1.1108755e+08 | E5: =SUM(Денежный_поток!I7:K9) -> 306287.48 | F5: =E5 -> 306287.48 | G5: =MAX(0,C5-D5) -> 24790172 | H5: =IF(F5=0,"",G5/F5) -> 80.937595 | I5: =IF(H5="","",IF(H5>=Вводные!$B29,"OK","RISK")) -> OK
A6: Q3 | B6: М7-М9 | C6: =SUM(Денежный_поток!H10:H12) -> 2.7685783e+08 | D6: =SUM(Денежный_поток!E10:E12) -> 1.373167e+08 | E6: =SUM(Денежный_поток!I10:K12) -> 239308.16 | F6: =E6 -> 239308.16 | G6: =MAX(0,C6-D6) -> 1.3954113e+08 | H6: =IF(F6=0,"",G6/F6) -> 583.10227 | I6: =IF(H6="","",IF(H6>=Вводные!$B29,"OK","RISK")) -> OK
A7: Q4 | B7: М10-М12 | C7: =SUM(Денежный_поток!H13:H15) -> 3.9825789e+08 | D7: =SUM(Денежный_поток!E13:E15) -> 2.8802764e+08 | E7: =SUM(Денежный_поток!I13:K15) -> 144021.45 | F7: =E7 -> 144021.45 | G7: =MAX(0,C7-D7) -> 1.1023025e+08 | H7: =IF(F7=0,"",G7/F7) -> 765.37382 | I7: =IF(H7="","",IF(H7>=Вводные!$B29,"OK","RISK")) -> OK
A8: Q5 | B8: М13-М15 | C8: =SUM(Денежный_поток!H16:H18) -> 4.3610174e+08 | D8: =SUM(Денежный_поток!E16:E18) -> 2.2857553e+08 | E8: =SUM(Денежный_поток!I16:K18) -> 100911.71 | F8: =E8 -> 100911.71 | G8: =MAX(0,C8-D8) -> 2.0752622e+08 | H8: =IF(F8=0,"",G8/F8) -> 2056.5128 | I8: =IF(H8="","",IF(H8>=Вводные!$B29,"OK","RISK")) -> OK
A9: Q6 | B9: М16-М18 | C9: =SUM(Денежный_поток!H19:H21) -> 1.4722121e+08 | D9: =SUM(Денежный_поток!E19:E21) -> 34304369 | E9: =SUM(Денежный_поток!I19:K21) -> 113598.96 | F9: =E9 -> 113598.96 | G9: =MAX(0,C9-D9) -> 1.1291684e+08 | H9: =IF(F9=0,"",G9/F9) -> 993.99537 | I9: =IF(H9="","",IF(H9>=Вводные!$B29,"OK","RISK")) -> OK
A10: Q7 | B10: М19-М21 | C10: =SUM(Денежный_поток!H22:H24) -> 0 | D10: =SUM(Денежный_поток!E22:E24) -> 0 | E10: =SUM(Денежный_поток!I22:K24) -> 268149.33 | F10: =E10 -> 268149.33 | G10: =MAX(0,C10-D10) -> 0 | H10: =IF(F10=0,"",G10/F10) -> 0 | I10: =IF(H10="","",IF(H10>=Вводные!$B29,"OK","RISK")) -> RISK
A11: Q8 | B11: М22-М24 | C11: =SUM(Денежный_поток!H25:H27) -> 0 | D11: =SUM(Денежный_поток!E25:E27) -> 0 | E11: =SUM(Денежный_поток!I25:K27) -> 267974.61 | F11: =E11 -> 267974.61 | G11: =MAX(0,C11-D11) -> 0 | H11: =IF(F11=0,"",G11/F11) -> 0 | I11: =IF(H11="","",IF(H11>=Вводные!$B29,"OK","RISK")) -> RISK
A12: Q9 | B12: М25-М27 | C12: =SUM(Денежный_поток!H28:H30) -> 0 | D12: =SUM(Денежный_поток!E28:E30) -> 0 | E12: =SUM(Денежный_поток!I28:K30) -> 267800.02 | F12: =E12 -> 267800.02 | G12: =MAX(0,C12-D12) -> 0 | H12: =IF(F12=0,"",G12/F12) -> 0 | I12: =IF(H12="","",IF(H12>=Вводные!$B29,"OK","RISK")) -> RISK
A13: Q10 | B13: М28-М30 | C13: =SUM(Денежный_поток!H31:H33) -> 0 | D13: =SUM(Денежный_поток!E31:E33) -> 0 | E13: =SUM(Денежный_поток!I31:K33) -> 267625.55 | F13: =E13 -> 267625.55 | G13: =MAX(0,C13-D13) -> 0 | H13: =IF(F13=0,"",G13/F13) -> 0 | I13: =IF(H13="","",IF(H13>=Вводные!$B29,"OK","RISK")) -> RISK
A14: Q11 | B14: М31-М33 | C14: =SUM(Денежный_поток!H34:H36) -> 0 | D14: =SUM(Денежный_поток!E34:E36) -> 0 | E14: =SUM(Денежный_поток!I34:K36) -> 267451.21 | F14: =E14 -> 267451.21 | G14: =MAX(0,C14-D14) -> 0 | H14: =IF(F14=0,"",G14/F14) -> 0 | I14: =IF(H14="","",IF(H14>=Вводные!$B29,"OK","RISK")) -> RISK
A15: Q12 | B15: М34-М36 | C15: =SUM(Денежный_поток!H37:H39) -> 0 | D15: =SUM(Денежный_поток!E37:E39) -> 0 | E15: =SUM(Денежный_поток!I37:K39) -> 267277 | F15: =E15 -> 267277 | G15: =MAX(0,C15-D15) -> 0 | H15: =IF(F15=0,"",G15/F15) -> 0 | I15: =IF(H15="","",IF(H15>=Вводные!$B29,"OK","RISK")) -> RISK

Sheet Свод
A1: СВОДНЫЕ ПОКАЗАТЕЛИ
A3: Показатель | B3: Значение | C3: Ед. | D3: Комментарий
A4: Выручка проекта | B4: =Продажи!J41 -> 1.4741871e+09 | C4: руб | D4: Итого выручка квартир и машиномест
A5: Стоимость проекта | B5: =Структура_затрат!H37 -> 1.0445998e+09 | C5: руб | D5: Итого главы 1-3
A6: Глава 1 | B6: =Структура_затрат!H8 -> 0 | C6: руб | D6: Земля и связанные расходы
A7: Глава 2 | B7: =Структура_затрат!H34 -> 1.0003742e+09 | C7: руб | D7: Строительство
A8: Глава 3 | B8: =Структура_затрат!H36 -> 44225613 | C8: руб | D8: Коммерческие расходы
A9: Маржа, руб | B9: =B4-B5 -> 4.295873e+08 | C9: руб | D9: Выручка минус стоимость
A10: Маржа, % | B10: =IF(B4=0,0,B9/B4) -> 0.29140623 | C10: %
A11: Себестоимость на 1 м2 GSA | B11: =B5/Вводные!$B$11 -> 132895.33 | C11: руб/м2
A12: Средняя цена продажи на 1 м2 | B12: =B4/Вводные!$B$11 -> 187547.97 | C12: руб/м2
A13: Пик долга | B13: =MAX(Кредит!S4:S39) -> 7.4105582e+08 | C13: руб
A14: Начисленные проценты | B14: =SUM(Кредит!N4:N39) -> 435985.63 | C14: руб
A15: Капитализированные проценты | B15: =SUM(Кредит!O4:O39) -> 324945.55 | C15: руб
A16: Проценты к оплате | B16: =SUM(Кредит!P4:P39) -> 111040.08 | C16: руб
A17: Комиссия банка | B17: =SUM(Кредит!Q4:Q39) -> 2586099.3 | C17: руб
A18: Минимальный DSCR | B18: =MIN(ДСCR!H4:H15) -> 0 | C18: x | D18: Смотреть лист ДСCR
A19: Доля собственных средств | B19: =SUM(Кредит!G4:G39)/(Структура_затрат!H8+Структура_затрат!H34) -> 0.13051861 | C19: %
A20: Остаток долга на конец модели | B20: =Кредит!S39 -> 7.4105582e+08 | C20: руб
A21: Итоговая маржа | B21: =B9-B9*0.25 -> 3.2219047e+08
A22: Примечание | B22: Модель построена в девелоперской логике и полностью на русском языке. Все статьи затрат считаются от м2.
A23: Примечание по исправлению | B23: Исправлены ссылки, вызывавшие #ЗНАЧ! во вкладке "Кредит", и логика погашения/раскрытия переведена на совпадение месяца, а не точной даты. | D23: Кредит / денежный поток / DSCR переведены в более жесткую девелоперскую логику: обслуживание долга идет из доступного cash-in после раскрытия эскроу.
